Workbook

Sheet Final Summary 
A1: Metrics | B1: Model 1 - GDP growth | C1: Model 2 - Unemployment | D1: Model 3 - Income growth
A2: Training Results (1980-2015)
A3: R2 | B3: ='Training Data'!P6 -> 0.20846616 | C3: ='Training Data'!P29 -> 0.24280363 | D3: ='Training Data'!P54 -> 0.99874142
A4: Adjusted R2 | B4: ='Training Data'!P7 -> 0.13425986 | C4: ='Training Data'!P30 -> 0.1739676 | D4: ='Training Data'!P55 -> 0.99862701
A5: F-statistic P-value | B5: ='Training Data'!T13 -> 0.055187726 | C5: ='Training Data'!T36 -> 0.025412066 | D5: ='Training Data'!T61 -> 6.5860689e-48
A6: Immigration Coefficient | B6: ='Training Data'!P19 -> -2.4616384e-06 | C6: ='Training Data'!P43 -> -3.6248466e-06 | D6: ='Training Data'!P67 -> -5.4751729e-05
A7: Immigration P-value | B7: ='Training Data'!S19 -> 0.52651081 | C7: ='Training Data'!S43 -> 0.73593184 | D7: ='Training Data'!S67 -> 0.34840962
A8: Immigration Significant | B8: NO | C8: NO | D8: NO
A10: Testing Results (2016-2021)
A11: MAE | B11: ='Testing Data'!B10 -> 7.9909778 | C11: ='Testing Data'!B17 -> 459064.64 | D11: ='Testing Data'!B23 -> 3450.0772
A12: RMSE | B12: ='Testing Data'!B11 -> 8.4314093 | C12: ='Testing Data'!B18 -> 478921.59 | D12: ='Testing Data'!B24 -> 3457.5303
A13: MAPE | B13: ='Testing Data'!B12 -> 2.2091694 | C13: ='Testing Data'!B19 -> 8420.2285 | D13: ='Testing Data'!B25 -> 0.16480243
A14: Conclusion | B14: NO, Significant impact | C14: NO, Significant impact | D14: NO, Significant impact
A16: Critical Factor Ranking
A17: Variable | B17: Model | C17: Coefficient | D17: P-value | E17: Effect on DV
A18: Net immigration | B18: Model 3 | C18: =$D$6 -> -5.4751729e-05 | D18: =$D$7 -> 0.34840962 | E18: No significant effect on Income Growth
A19: Net immigration | B19: Model 2 | C19: =$C$6 -> -3.6248466e-06 | D19: =$C$7 -> 0.73593184 | E19: No significant effect on Unemployment
A20: Net immigration | B20: Model 1 | C20: =$B$6 -> -2.4616384e-06 | D20: =$B$7 -> 0.52651081 | E20: No significant effect on GDP Growth
A21: Unemployment Rate | B21: Model 1 | C21: ='Training Data'!$P$20 -> 0.10181284 | D21: ='Training Data'!$S$20 -> 0.10370822 | E21: Marginal positive effect on GDP Growth (not significant)
A22: GDP Growth Ranking | B22: Model 2 | C22: ='Training Data'!$P$42 -> 0.76536121 | D22: ='Training Data'!$S$42 -> 0.10969376 | E22: Marginal positive effect on Unemployment (not significant)
A23: GDP Nominal | B23: Model 3 | C23: ='Training Data'!$P$68 -> 0.84797794 | D23: ='Training Data'!$S$68 -> 1.0242023e-47 | E23: Strong positive effect on Income Growth (HIGHLY SIGNIFICANT)
A24: Unemployment Rate | B24: Model 3 | C24: ='Training Data'!$P$69 -> 3.2317381 | D24: ='Training Data'!$S$69 -> 0.025316355 | E24: Significant positive effect on Income Growth
A28: Critical Factor Ranking based on P-value
A29: Variable | B29: Model | C29: Coefficient | D29: P-value | E29: Effect on DV
A30: GDP Nominal | B30: Model 3 | C30: ='Training Data'!$P$68 -> 0.84797794 | D30: ='Training Data'!$S$68 -> 1.0242023e-47 | E30: EXTREMELY strong positive effect on Income Growth. Each $1B increase in GDP → 0.85% increase in personal income growth. HIGHLY SIGNIFICANT.
A31: Unemployment Rate | B31: Model 3 | C31: ='Training Data'!$P$69 -> 3.2317381 | D31: ='Training Data'!$S$69 -> 0.025316355 | E31: Significant positive effect on Income Growth. 1 percentage point increase in unemployment → 3.23% increase in income growth (counterintuitive - may reflect wage inflation during tight labor markets).
A32: Unemployment Rate | B32: Model 1 | C32: ='Training Data'!$P$20 -> 0.10181284 | D32: ='Training Data'!$S$20 -> 0.10370822 | E32: Marginal effect on GDP Growth. Not statistically significant at 5% level, but close (marginal at 10% level).
A33: GDP Growth Ranking | B33: Model 2 | C33: ='Training Data'!$P$42 -> 0.76536121 | D33: ='Training Data'!$S$42 -> 0.10969376 | E33: Marginal effect on Unemployment. Not significant, but shows trend: higher GDP growth → higher unemployment
A34: Net immigration | B34: Model 3 | C34: =$D$6 -> -5.4751729e-05 | D34: =$D$7 -> 0.34840962 | E34: No significant effect on Income Growth
A35: Net immigration | B35: Model 1 | C35: =$B$6 -> -2.4616384e-06 | D35: =$B$7 -> 0.52651081 | E35: No significant effect on GDP Growth
A36: Net immigration | B36: Model 2 | C36: =$C$6 -> -3.6248466e-06 | D36: =$C$7 -> 0.73593184 | E36: No significant effect on Unemployment

Sheet Master Dataset
A1: Year | B1: Net Immigration | C1: Immigration Rate | D1: GDP Nominal | E1: GDP Growth Rate | F1: Personal Income | G1: Unemployment Rate | H1: Immigration Lag1 | I1: GDP lag1 | K1: Net Immigration | L1: =G1 -> Unemployment Rate | M1: =H1 -> Immigration Lag1 | O1: =G1 -> Unemployment Rate | P1: =E1 -> GDP Growth Rate | Q1: =B1 -> Net Immigration | R1: =H1 -> Immigration Lag1 | T1: =F1 -> Personal Income | U1: =B1 -> Net Immigration | V1: =D1 -> GDP Nominal | W1: =G1 -> Unemployment Rate
A2: 1980 | B2: =VLOOKUP(A2,'Raw_Imigration data'!A:G, 7, FALSE) -> -5813 | C2: =VLOOKUP(A2,'Raw_Imigration data'!A:H, 8, FALSE) -> -2325.2 | D2: ='Raw_Gross Domestic Product '!B3 -> 2857.3 | F2: ='Raw_Personal Income and Its Dis'!C3 -> 2324.5 | G2: =Raw_Unemployment!B2 -> 86.1 | K2: =B2 -> -5813 | L2: =G2 -> 86.1 | M2: =H2 -> 0 | O2: =G2 -> 86.1 | P2: =E2 -> 0 | Q2: =B2 -> -5813 | R2: =H2 -> 0 | T2: =F2 -> 2324.5 | U2: =B2 -> -5813 | V2: =D2 -> 2857.3 | W2: =G2 -> 86.1
A3: 1981 | B3: =VLOOKUP(A3,'Raw_Imigration data'!A:G, 7, FALSE) -> -86988 | C3: =VLOOKUP(A3,'Raw_Imigration data'!A:H, 8, FALSE) -> -34795.2 | D3: ='Raw_Gross Domestic Product '!C3 -> 3207 | E3: =((D3-D2)/D2)*100 -> 12.238827 | F3: ='Raw_Personal Income and Its Dis'!D3 -> 2603.2 | G3: =Raw_Unemployment!B3 -> 91.4 | H3: =B2 -> -5813 | I3: =E2 -> 0 | K3: =B3 -> -86988 | L3: =G3 -> 91.4 | M3: =H3 -> -5813 | O3: =G3 -> 91.4 | P3: =E3 -> 12.238827 | Q3: =B3 -> -86988 | R3: =H3 -> -5813 | T3: =F3 -> 2603.2 | U3: =B3 -> -86988 | V3: =D3 -> 3207 | W3: =G3 -> 91.4
A4: 1982 | B4: =VLOOKUP(A4,'Raw_Imigration data'!A:G, 7, FALSE) -> -196068 | C4: =VLOOKUP(A4,'Raw_Imigration data'!A:H, 8, FALSE) -> -78427.2 | D4: ='Raw_Gross Domestic Product '!D3 -> 3343.8 | E4: =((D4-D3)/D3)*100 -> 4.2656688 | F4: ='Raw_Personal Income and Its Dis'!E3 -> 2789.5 | G4: =Raw_Unemployment!B4 -> 116.5 | H4: =B3 -> -86988 | I4: =E3 -> 12.238827 | K4: =B4 -> -196068 | L4: =G4 -> 116.5 | M4: =H4 -> -86988 | O4: =G4 -> 116.5 | P4: =E4 -> 4.2656688 | Q4: =B4 -> -196068 | R4: =H4 -> -86988 | T4: =F4 -> 2789.5 | U4: =B4 -> -196068 | V4: =D4 -> 3343.8 | W4: =G4 -> 116.5
A5: 1983 | B5: =VLOOKUP(A5,'Raw_Imigration data'!A:G, 7, FALSE) -> -339541 | C5: =VLOOKUP(A5,'Raw_Imigration data'!A:H, 8, FALSE) -> -135816.4 | D5: ='Raw_Gross Domestic Product '!E3 -> 3634 | E5: =((D5-D4)/D4)*100 -> 8.6787487 | F5: ='Raw_Personal Income and Its Dis'!F3 -> 2981.7 | G5: =Raw_Unemployment!B5 -> 115.2 | H5: =B4 -> -196068 | I5: =E4 -> 4.2656688 | K5: =B5 -> -339541 | L5: =G5 -> 115.2 | M5: =H5 -> -196068 | O5: =G5 -> 115.2 | P5: =E5 -> 8.6787487 | Q5: =B5 -> -339541 | R5: =H5 -> -196068 | T5: =F5 -> 2981.7 | U5: =B5 -> -339541 | V5: =D5 -> 3634 | W5: =G5 -> 115.2
A6: 1984 | B6: =VLOOKUP(A6,'Raw_Imigration data'!A:G, 7, FALSE) -> -316325 | C6: =VLOOKUP(A6,'Raw_Imigration data'!A:H, 8, FALSE) -> -126530 | D6: ='Raw_Gross Domestic Product '!F3 -> 4037.6 | E6: =((D6-D5)/D5)*100 -> 11.106219 | F6: ='Raw_Personal Income and Its Dis'!G3 -> 3288.7 | G6: =Raw_Unemployment!B6 -> 90.1 | H6: =B5 -> -339541 | I6: =E5 -> 8.6787487 | K6: =B6 -> -316325 | L6: =G6 -> 90.1 | M6: =H6 -> -339541 | O6: =G6 -> 90.1 | P6: =E6 -> 11.106219 | Q6: =B6 -> -316325 | R6: =H6 -> -339541 | T6: =F6 -> 3288.7 | U6: =B6 -> -316325 | V6: =D6 -> 4037.6 | W6: =G6 -> 90.1
A7: 1985 | B7: =VLOOKUP(A7,'Raw_Imigration data'!A:G, 7, FALSE) -> -428548 | C7: =VLOOKUP(A7,'Raw_Imigration data'!A:H, 8, FALSE) -> -171419.2 | D7: ='Raw_Gross Domestic Product '!G3 -> 4339 | E7: =((D7-D6)/D6)*100 -> 7.4648306 | F7: ='Raw_Personal Income and Its Dis'!H3 -> 3522.9 | G7: =Raw_Unemployment!B7 -> 86.3 | H7: =B6 -> -316325 | I7: =E6 -> 11.106219 | K7: =B7 -> -428548 | L7: =G7 -> 86.3 | M7: =H7 -> -316325 | O7: =G7 -> 86.3 | P7: =E7 -> 7.4648306 | Q7: =B7 -> -428548 | R7: =H7 -> -316325 | T7: =F7 -> 3522.9 | U7: =B7 -> -428548 | V7: =D7 -> 4339 | W7: =G7 -> 86.3
A8: 1986 | B8: =VLOOKUP(A8,'Raw_Imigration data'!A:G, 7, FALSE) -> -948739 | C8: =VLOOKUP(A8,'Raw_Imigration data'!A:H, 8, FALSE) -> -379495.6 | D8: ='Raw_Gross Domestic Product '!H3 -> 4579.6 | E8: =((D8-D7)/D7)*100 -> 5.5450565 | F8: ='Raw_Personal Income and Its Dis'!I3 -> 3731.2 | G8: =Raw_Unemployment!B8 -> 84 | H8: =B7 -> -428548 | I8: =E7 -> 7.4648306 | K8: =B8 -> -948739 | L8: =G8 -> 84 | M8: =H8 -> -428548 | O8: =G8 -> 84 | P8: =E8 -> 5.5450565 | Q8: =B8 -> -948739 | R8: =H8 -> -428548 | T8: =F8 -> 3731.2 | U8: =B8 -> -948739 | V8: =D8 -> 4579.6 | W8: =G8 -> 84
A9: 1987 | B9: =VLOOKUP(A9,'Raw_Imigration data'!A:G, 7, FALSE) -> -451122 | C9: =VLOOKUP(A9,'Raw_Imigration data'!A:H, 8, FALSE) -> -180448.8 | D9: ='Raw_Gross Domestic Product '!I3 -> 4855.2 | E9: =((D9-D8)/D8)*100 -> 6.0179928 | F9: ='Raw_Personal Income and Its Dis'!J3 -> 3946.8 | G9: =Raw_Unemployment!B9 -> 74.1 | H9: =B8 -> -948739 | I9: =E8 -> 5.5450565 | K9: =B9 -> -451122 | L9: =G9 -> 74.1 | M9: =H9 -> -948739 | O9: =G9 -> 74.1 | P9: =E9 -> 6.0179928 | Q9: =B9 -> -451122 | R9: =H9 -> -948739 | T9: =F9 -> 3946.8 | U9: =B9 -> -451122 | V9: =D9 -> 4855.2 | W9: =G9 -> 74.1
A10: 1988 | B10: =VLOOKUP(A10,'Raw_Imigration data'!A:G, 7, FALSE) -> -219790 | C10: =VLOOKUP(A10,'Raw_Imigration data'!A:H, 8, FALSE) -> -87916 | D10: ='Raw_Gross Domestic Product '!J3 -> 5236.4 | E10: =((D10-D9)/D9)*100 -> 7.8513758 | F10: ='Raw_Personal Income and Its Dis'!K3 -> 4280 | G10: =Raw_Unemployment!B10 -> 65.9 | H10: =B9 -> -451122 | I10: =E9 -> 6.0179928 | K10: =B10 -> -219790 | L10: =G10 -> 65.9 | M10: =H10 -> -451122 | O10: =G10 -> 65.9 | P10: =E10 -> 7.8513758 | Q10: =B10 -> -219790 | R10: =H10 -> -451122 | T10: =F10 -> 4280 | U10: =B10 -> -219790 | V10: =D10 -> 5236.4 | W10: =G10 -> 65.9
A11: 1989 | B11: =VLOOKUP(A11,'Raw_Imigration data'!A:G, 7, FALSE) -> 331925 | C11: =VLOOKUP(A11,'Raw_Imigration data'!A:H, 8, FALSE) -> 132770 | D11: ='Raw_Gross Domestic Product '!K3 -> 5641.6 | E11: =((D11-D10)/D10)*100 -> 7.7381407 | F11: ='Raw_Personal Income and Its Dis'!L3 -> 4621 | G11: =Raw_Unemployment!B11 -> 63.1 | H11: =B10 -> -219790 | I11: =E10 -> 7.8513758 | K11: =B11 -> 331925 | L11: =G11 -> 63.1 | M11: =H11 -> -219790 | O11: =G11 -> 63.1 | P11: =E11 -> 7.7381407 | Q11: =B11 -> 331925 | R11: =H11 -> -219790 | T11: =F11 -> 4621 | U11: =B11 -> 331925 | V11: =D11 -> 5641.6 | W11: =G11 -> 63.1
A12: 1990 | B12: =VLOOKUP(A12,'Raw_Imigration data'!A:G, 7, FALSE) -> 605366 | C12: =VLOOKUP(A12,'Raw_Imigration data'!A:H, 8, FALSE) -> 242146.4 | D12: ='Raw_Gross Domestic Product '!L3 -> 5963.1 | E12: =((D12-D11)/D11)*100 -> 5.6987379 | F12: ='Raw_Personal Income and Its Dis'!M3 -> 4913.3 | G12: =Raw_Unemployment!B12 -> 67.4 | H12: =B11 -> 331925 | I12: =E11 -> 7.7381407 | K12: =B12 -> 605366 | L12: =G12 -> 67.4 | M12: =H12 -> 331925 | O12: =G12 -> 67.4 | P12: =E12 -> 5.6987379 | Q12: =B12 -> 605366 | R12: =H12 -> 331925 | T12: =F12 -> 4913.3 | U12: =B12 -> 605366 | V12: =D12 -> 5963.1 | W12: =G12 -> 67.4
A13: 1991 | B13: =VLOOKUP(A13,'Raw_Imigration data'!A:G, 7, FALSE) -> 845690 | C13: =VLOOKUP(A13,'Raw_Imigration data'!A:H, 8, FALSE) -> 338276 | D13: ='Raw_Gross Domestic Product '!M3 -> 6158.1 | E13: =((D13-D12)/D12)*100 -> 3.2701112 | F13: ='Raw_Personal Income and Its Dis'!N3 -> 5089.9 | G13: =Raw_Unemployment!B13 -> 82.2 | H13: =B12 -> 605366 | I13: =E12 -> 5.6987379 | K13: =B13 -> 845690 | L13: =G13 -> 82.2 | M13: =H13 -> 605366 | O13: =G13 -> 82.2 | P13: =E13 -> 3.2701112 | Q13: =B13 -> 845690 | R13: =H13 -> 605366 | T13: =F13 -> 5089.9 | U13: =B13 -> 845690 | V13: =D13 -> 6158.1 | W13: =G13 -> 82.2
A14: 1992 | B14: =VLOOKUP(A14,'Raw_Imigration data'!A:G, 7, FALSE) -> -60507 | C14: =VLOOKUP(A14,'Raw_Imigration data'!A:H, 8, FALSE) -> -24202.8 | D14: ='Raw_Gross Domestic Product '!N3 -> 6520.3 | E14: =((D14-D13)/D13)*100 -> 5.8816843 | F14: ='Raw_Personal Income and Its Dis'!O3 -> 5417.5 | G14: =Raw_Unemployment!B14 -> 89.9 | H14: =B13 -> 845690 | I14: =E13 -> 3.2701112 | K14: =B14 -> -60507 | L14: =G14 -> 89.9 | M14: =H14 -> 845690 | O14: =G14 -> 89.9 | P14: =E14 -> 5.8816843 | Q14: =B14 -> -60507 | R14: =H14 -> 845690 | T14: =F14 -> 5417.5 | U14: =B14 -> -60507 | V14: =D14 -> 6520.3 | W14: =G14 -> 89.9
A15: 1993 | B15: =VLOOKUP(A15,'Raw_Imigration data'!A:G, 7, FALSE) -> -267855 | C15: =VLOOKUP(A15,'Raw_Imigration data'!A:H, 8, FALSE) -> -107142 | D15: ='Raw_Gross Domestic Product '!O3 -> 6858.6 | E15: =((D15-D14)/D14)*100 -> 5.1884116 | F15: ='Raw_Personal Income and Its Dis'!P3 -> 5652.9 | G15: =Raw_Unemployment!B15 -> 82.9 | H15: =B14 -> -60507 | I15: =E14 -> 5.8816843 | K15: =B15 -> -267855 | L15: =G15 -> 82.9 | M15: =H15 -> -60507 | O15: =G15 -> 82.9 | P15: =E15 -> 5.1884116 | Q15: =B15 -> -267855 | R15: =H15 -> -60507 | T15: =F15 -> 5652.9 | U15: =B15 -> -267855 | V15: =D15 -> 6858.6 | W15: =G15 -> 82.9
A16: 1994 | B16: =VLOOKUP(A16,'Raw_Imigration data'!A:G, 7, FALSE) -> -159108 | C16: =VLOOKUP(A16,'Raw_Imigration data'!A:H, 8, FALSE) -> -63643.2 | D16: ='Raw_Gross Domestic Product '!P3 -> 7287.2 | E16: =((D16-D15)/D15)*100 -> 6.2490887 | F16: ='Raw_Personal Income and Its Dis'!Q3 -> 5940.9 | G16: =Raw_Unemployment!B16 -> 73.2 | H16: =B15 -> -267855 | I16: =E15 -> 5.1884116 | K16: =B16 -> -159108 | L16: =G16 -> 73.2 | M16: =H16 -> -267855 | O16: =G16 -> 73.2 | P16: =E16 -> 6.2490887 | Q16: =B16 -> -159108 | R16: =H16 -> -267855 | T16: =F16 -> 5940.9 | U16: =B16 -> -159108 | V16: =D16 -> 7287.2 | W16: =G16 -> 73.2
A17: 1995 | B17: =VLOOKUP(A17,'Raw_Imigration data'!A:G, 7, FALSE) -> -545538 | C17: =VLOOKUP(A17,'Raw_Imigration data'!A:H, 8, FALSE) -> -218215.2 | D17: ='Raw_Gross Domestic Product '!Q3 -> 7639.7 | E17: =((D17-D16)/D16)*100 -> 4.8372489 | F17: ='Raw_Personal Income and Its Dis'!R3 -> 6283.4 | G17: =Raw_Unemployment!B17 -> 67.1 | H17: =B16 -> -159108 | I17: =E16 -> 6.2490887 | K17: =B17 -> -545538 | L17: =G17 -> 67.1 | M17: =H17 -> -159108 | O17: =G17 -> 67.1 | P17: =E17 -> 4.8372489 | Q17: =B17 -> -545538 | R17: =H17 -> -159108 | T17: =F17 -> 6283.4 | U17: =B17 -> -545538 | V17: =D17 -> 7639.7 | W17: =G17 -> 67.1
A18: 1996 | B18: =VLOOKUP(A18,'Raw_Imigration data'!A:G, 7, FALSE) -> -652127 | C18: =VLOOKUP(A18,'Raw_Imigration data'!A:H, 8, FALSE) -> -260850.8 | D18: ='Raw_Gross Domestic Product '!R3 -> 8073.1 | E18: =((D18-D17)/D17)*100 -> 5.6729976 | F18: ='Raw_Personal Income and Its Dis'!S3 -> 6666.2 | G18: =Raw_Unemployment!B18 -> 64.9 | H18: =B17 -> -545538 | I18: =E17 -> 4.8372489 | K18: =B18 -> -652127 | L18: =G18 -> 64.9 | M18: =H18 -> -545538 | O18: =G18 -> 64.9 | P18: =E18 -> 5.6729976 | Q18: =B18 -> -652127 | R18: =H18 -> -545538 | T18: =F18 -> 6666.2 | U18: =B18 -> -652127 | V18: =D18 -> 8073.1 | W18: =G18 -> 64.9
A19: 1997 | B19: =VLOOKUP(A19,'Raw_Imigration data'!A:G, 7, FALSE) -> -687616 | C19: =VLOOKUP(A19,'Raw_Imigration data'!A:H, 8, FALSE) -> -275046.4 | D19: ='Raw_Gross Domestic Product '!S3 -> 8577.6 | E19: =((D19-D18)/D18)*100 -> 6.2491484 | F19: ='Raw_Personal Income and Its Dis'!T3 -> 7074 | G19: =Raw_Unemployment!B19 -> 59.3 | H19: =B18 -> -652127 | I19: =E18 -> 5.6729976 | K19: =B19 -> -687616 | L19: =G19 -> 59.3 | M19: =H19 -> -652127 | O19: =G19 -> 59.3 | P19: =E19 -> 6.2491484 | Q19: =B19 -> -687616 | R19: =H19 -> -652127 | T19: =F19 -> 7074 | U19: =B19 -> -687616 | V19: =D19 -> 8577.6 | W19: =G19 -> 59.3
A20: 1998 | B20: =VLOOKUP(A20,'Raw_Imigration data'!A:G, 7, FALSE) -> -1015022 | C20: =VLOOKUP(A20,'Raw_Imigration data'!A:H, 8, FALSE) -> -406008.8 | D20: ='Raw_Gross Domestic Product '!T3 -> 9062.8 | E20: =((D20-D19)/D19)*100 -> 5.6565939 | F20: ='Raw_Personal Income and Its Dis'!U3 -> 7588.4 | G20: =Raw_Unemployment!B20 -> 54 | H20: =B19 -> -687616 | I20: =E19 -> 6.2491484 | K20: =B20 -> -1015022 | L20: =G20 -> 54 | M20: =H20 -> -687616 | O20: =G20 -> 54 | P20: =E20 -> 5.6565939 | Q20: =B20 -> -1015022 | R20: =H20 -> -687616 | T20: =F20 -> 7588.4 | U20: =B20 -> -1015022 | V20: =D20 -> 9062.8 | W20: =G20 -> 54
A21: 1999 | B21: =VLOOKUP(A21,'Raw_Imigration data'!A:G, 7, FALSE) -> -1027905 | C21: =VLOOKUP(A21,'Raw_Imigration data'!A:H, 8, FALSE) -> -411162 | D21: ='Raw_Gross Domestic Product '!U3 -> 9631.2 | E21: =((D21-D20)/D20)*100 -> 6.2717924 | F21: ='Raw_Personal Income and Its Dis'!V3 -> 7978.6 | G21: =Raw_Unemployment!B21 -> 50.6 | H21: =B20 -> -1015022 | I21: =E20 -> 5.6565939 | K21: =B21 -> -1027905 | L21: =G21 -> 50.6 | M21: =H21 -> -1015022 | O21: =G21 -> 50.6 | P21: =E21 -> 6.2717924 | Q21: =B21 -> -1027905 | R21: =H21 -> -1015022 | T21: =F21 -> 7978.6 | U21: =B21 -> -1027905 | V21: =D21 -> 9631.2 | W21: =G21 -> 50.6
A22: 2000 | B22: =VLOOKUP(A22,'Raw_Imigration data'!A:G, 7, FALSE) -> -951176 | C22: =VLOOKUP(A22,'Raw_Imigration data'!A:H, 8, FALSE) -> -380470.4 | D22: ='Raw_Gross Domestic Product '!V3 -> 10251 | E22: =((D22-D21)/D21)*100 -> 6.4353352 | F22: ='Raw_Personal Income and Its Dis'!W3 -> 8621.3 | G22: =Raw_Unemployment!B22 -> 47.6 | H22: =B21 -> -1027905 | I22: =E21 -> 6.2717924 | K22: =B22 -> -951176 | L22: =G22 -> 47.6 | M22: =H22 -> -1027905 | O22: =G22 -> 47.6 | P22: =E22 -> 6.4353352 | Q22: =B22 -> -951176 | R22: =H22 -> -1027905 | T22: =F22 -> 8621.3 | U22: =B22 -> -951176 | V22: =D22 -> 10251 | W22: =G22 -> 47.6
A23: 2001 | B23: =VLOOKUP(A23,'Raw_Imigration data'!A:G, 7, FALSE) -> -410575 | C23: =VLOOKUP(A23,'Raw_Imigration data'!A:H, 8, FALSE) -> -164230 | D23: ='Raw_Gross Domestic Product '!W3 -> 10581.9 | E23: =((D23-D22)/D22)*100 -> 3.2279778 | F23: ='Raw_Personal Income and Its Dis'!X3 -> 8993.1 | G23: =Raw_Unemployment!B23 -> 56.9 | H23: =B22 -> -951176 | I23: =E22 -> 6.4353352 | K23: =B23 -> -410575 | L23: =G23 -> 56.9 | M23: =H23 -> -951176 | O23: =G23 -> 56.9 | P23: =E23 -> 3.2279778 | Q23: =B23 -> -410575 | R23: =H23 -> -951176 | T23: =F23 -> 8993.1 | U23: =B23 -> -410575 | V23: =D23 -> 10581.9 | W23: =G23 -> 56.9
A24: 2002 | B24: =VLOOKUP(A24,'Raw_Imigration data'!A:G, 7, FALSE) -> -91143 | C24: =VLOOKUP(A24,'Raw_Imigration data'!A:H, 8, FALSE) -> -36457.2 | D24: ='Raw_Gross Domestic Product '!X3 -> 10929.1 | E24: =((D24-D23)/D23)*100 -> 3.2810743 | F24: ='Raw_Personal Income and Its Dis'!Y3 -> 9150 | G24: =Raw_Unemployment!B24 -> 69.4 | H24: =B23 -> -410575 | I24: =E23 -> 3.2279778 | K24: =B24 -> -91143 | L24: =G24 -> 69.4 | M24: =H24 -> -410575 | O24: =G24 -> 69.4 | P24: =E24 -> 3.2810743 | Q24: =B24 -> -91143 | R24: =H24 -> -410575 | T24: =F24 -> 9150 | U24: =B24 -> -91143 | V24: =D24 -> 10929.1 | W24: =G24 -> 69.4
A25: 2003 | B25: =VLOOKUP(A25,'Raw_Imigration data'!A:G, 7, FALSE) -> -424564 | C25: =VLOOKUP(A25,'Raw_Imigration data'!A:H, 8, FALSE) -> -169825.6 | D25: ='Raw_Gross Domestic Product '!Y3 -> 11456.5 | E25: =((D25-D24)/D24)*100 -> 4.825649 | F25: ='Raw_Personal Income and Its Dis'!Z3 -> 9481.8 | G25: =Raw_Unemployment!B25 -> 71.9 | H25: =B24 -> -91143 | I25: =E24 -> 3.2810743 | K25: =B25 -> -424564 | L25: =G25 -> 71.9 | M25: =H25 -> -91143 | O25: =G25 -> 71.9 | P25: =E25 -> 4.825649 | Q25: =B25 -> -424564 | R25: =H25 -> -91143 | T25: =F25 -> 9481.8 | U25: =B25 -> -424564 | V25: =D25 -> 11456.5 | W25: =G25 -> 71.9
A26: 2004 | B26: =VLOOKUP(A26,'Raw_Imigration data'!A:G, 7, FALSE) -> -396518 | C26: =VLOOKUP(A26,'Raw_Imigration data'!A:H, 8, FALSE) -> -158607.2 | D26: ='Raw_Gross Domestic Product '!Z3 -> 12217.2 | E26: =((D26-D25)/D25)*100 -> 6.6398987 | F26: ='Raw_Personal Income and Its Dis'!AA3 -> 10015.9 | G26: =Raw_Unemployment!B26 -> 66.5 | H26: =B25 -> -424564 | I26: =E25 -> 4.825649 | K26: =B26 -> -396518 | L26: =G26 -> 66.5 | M26: =H26 -> -424564 | O26: =G26 -> 66.5 | P26: =E26 -> 6.6398987 | Q26: =B26 -> -396518 | R26: =H26 -> -424564 | T26: =F26 -> 10015.9 | U26: =B26 -> -396518 | V26: =D26 -> 12217.2 | W26: =G26 -> 66.5
A27: 2005 | B27: =VLOOKUP(A27,'Raw_Imigration data'!A:G, 7, FALSE) -> -167356 | C27: =VLOOKUP(A27,'Raw_Imigration data'!A:H, 8, FALSE) -> -66942.4 | D27: ='Raw_Gross Domestic Product '!AA3 -> 13039.2 | E27: =((D27-D26)/D26)*100 -> 6.7282192 | F27: ='Raw_Personal Income and Its Dis'!AB3 -> 10546.1 | G27: =Raw_Unemployment!B27 -> 61 | H27: =B26 -> -396518 | I27: =E26 -> 6.6398987 | K27: =B27 -> -167356 | L27: =G27 -> 61 | M27: =H27 -> -396518 | O27: =G27 -> 61 | P27: =E27 -> 6.7282192 | Q27: =B27 -> -167356 | R27: =H27 -> -396518 | T27: =F27 -> 10546.1 | U27: =B27 -> -167356 | V27: =D27 -> 13039.2 | W27: =G27 -> 61
A28: 2006 | B28: =VLOOKUP(A28,'Raw_Imigration data'!A:G, 7, FALSE) -> -17132 | C28: =VLOOKUP(A28,'Raw_Imigration data'!A:H, 8, FALSE) -> -6852.8 | D28: ='Raw_Gross Domestic Product '!AB3 -> 13815.6 | E28: =((D28-D27)/D27)*100 -> 5.954353 | F28: ='Raw_Personal Income and Its Dis'!AC3 -> 11302 | G28: =Raw_Unemployment!B28 -> 55.3 | H28: =B27 -> -167356 | I28: =E27 -> 6.7282192 | K28: =B28 -> -17132 | L28: =G28 -> 55.3 | M28: =H28 -> -167356 | O28: =G28 -> 55.3 | P28: =E28 -> 5.954353 | Q28: =B28 -> -17132 | R28: =H28 -> -167356 | T28: =F28 -> 11302 | U28: =B28 -> -17132 | V28: =D28 -> 13815.6 | W28: =G28 -> 55.3
A29: 2007 | B29: =VLOOKUP(A29,'Raw_Imigration data'!A:G, 7, FALSE) -> -110139 | C29: =VLOOKUP(A29,'Raw_Imigration data'!A:H, 8, FALSE) -> -44055.6 | D29: ='Raw_Gross Domestic Product '!AC3 -> 14474.2 | E29: =((D29-D28)/D28)*100 -> 4.7670749 | F29: ='Raw_Personal Income and Its Dis'!AD3 -> 11932.1 | G29: =Raw_Unemployment!B29 -> 55.4 | H29: =B28 -> -17132 | I29: =E28 -> 5.954353 | K29: =B29 -> -110139 | L29: =G29 -> 55.4 | M29: =H29 -> -17132 | O29: =G29 -> 55.4 | P29: =E29 -> 4.7670749 | Q29: =B29 -> -110139 | R29: =H29 -> -17132 | T29: =F29 -> 11932.1 | U29: =B29 -> -110139 | V29: =D29 -> 14474.2 | W29: =G29 -> 55.4
A30: 2008 | B30: =VLOOKUP(A30,'Raw_Imigration data'!A:G, 7, FALSE) -> -3825 | C30: =VLOOKUP(A30,'Raw_Imigration data'!A:H, 8, FALSE) -> -1530 | D30: ='Raw_Gross Domestic Product '!AD3 -> 14769.9 | E30: =((D30-D29)/D29)*100 -> 2.0429454 | F30: ='Raw_Personal Income and Its Dis'!AE3 -> 12425.7 | G30: =Raw_Unemployment!B30 -> 69.6 | H30: =B29 -> -110139 | I30: =E29 -> 4.7670749 | K30: =B30 -> -3825 | L30: =G30 -> 69.6 | M30: =H30 -> -110139 | O30: =G30 -> 69.6 | P30: =E30 -> 2.0429454 | Q30: =B30 -> -3825 | R30: =H30 -> -110139 | T30: =F30 -> 12425.7 | U30: =B30 -> -3825 | V30: =D30 -> 14769.9 | W30: =G30 -> 69.6
A31: 2009 | B31: =VLOOKUP(A31,'Raw_Imigration data'!A:G, 7, FALSE) -> 243114 | C31: =VLOOKUP(A31,'Raw_Imigration data'!A:H, 8, FALSE) -> 97245.6 | D31: ='Raw_Gross Domestic Product '!AE3 -> 14478.1 | E31: =((D31-D30)/D30)*100 -> -1.9756396 | F31: ='Raw_Personal Income and Its Dis'!AF3 -> 12065.7 | G31: =Raw_Unemployment!B31 -> 111.4 | H31: =B30 -> -3825 | I31: =E30 -> 2.0429454 | K31: =B31 -> 243114 | L31: =G31 -> 111.4 | M31: =H31 -> -3825 | O31: =G31 -> 111.4 | P31: =E31 -> -1.9756396 | Q31: =B31 -> 243114 | R31: =H31 -> -3825 | T31: =F31 -> 12065.7 | U31: =B31 -> 243114 | V31: =D31 -> 14478.1 | W31: =G31 -> 111.4
A32: 2010 | B32: =VLOOKUP(A32,'Raw_Imigration data'!A:G, 7, FALSE) -> 261671 | C32: =VLOOKUP(A32,'Raw_Imigration data'!A:H, 8, FALSE) -> 104668.4 | D32: ='Raw_Gross Domestic Product '!AF3 -> 15049 | E32: =((D32-D31)/D31)*100 -> 3.943197 | F32: ='Raw_Personal Income and Its Dis'!AG3 -> 12556.6 | G32: =Raw_Unemployment!B32 -> 115.3 | H32: =B31 -> 243114 | I32: =E31 -> -1.9756396 | K32: =B32 -> 261671 | L32: =G32 -> 115.3 | M32: =H32 -> 243114 | O32: =G32 -> 115.3 | P32: =E32 -> 3.943197 | Q32: =B32 -> 261671 | R32: =H32 -> 243114 | T32: =F32 -> 12556.6 | U32: =B32 -> 261671 | V32: =D32 -> 15049 | W32: =G32 -> 115.3
A33: 2011 | B33: =VLOOKUP(A33,'Raw_Imigration data'!A:G, 7, FALSE) -> 405965 | C33: =VLOOKUP(A33,'Raw_Imigration data'!A:H, 8, FALSE) -> 162386 | D33: ='Raw_Gross Domestic Product '!AG3 -> 15599.7 | E33: =((D33-D32)/D32)*100 -> 3.6593794 | F33: ='Raw_Personal Income and Its Dis'!AH3 -> 13309.6 | G33: =Raw_Unemployment!B33 -> 107.2 | H33: =B32 -> 261671 | I33: =E32 -> 3.943197 | K33: =B33 -> 405965 | L33: =G33 -> 107.2 | M33: =H33 -> 261671 | O33: =G33 -> 107.2 | P33: =E33 -> 3.6593794 | Q33: =B33 -> 405965 | R33: =H33 -> 261671 | T33: =F33 -> 13309.6 | U33: =B33 -> 405965 | V33: =D33 -> 15599.7 | W33: =G33 -> 107.2
A34: 2012 | B34: =VLOOKUP(A34,'Raw_Imigration data'!A:G, 7, FALSE) -> 443126 | C34: =VLOOKUP(A34,'Raw_Imigration data'!A:H, 8, FALSE) -> 177250.4 | D34: ='Raw_Gross Domestic Product '!AH3 -> 16254 | E34: =((D34-D33)/D33)*100 -> 4.1943114 | F34: ='Raw_Personal Income and Its Dis'!AI3 -> 13917.8 | G34: =Raw_Unemployment!B34 -> 96.9 | H34: =B33 -> 405965 | I34: =E33 -> 3.6593794 | K34: =B34 -> 443126 | L34: =G34 -> 96.9 | M34: =H34 -> 405965 | O34: =G34 -> 96.9 | P34: =E34 -> 4.1943114 | Q34: =B34 -> 443126 | R34: =H34 -> 405965 | T34: =F34 -> 13917.8 | U34: =B34 -> 443126 | V34: =D34 -> 16254 | W34: =G34 -> 96.9
A35: 2013 | B35: =VLOOKUP(A35,'Raw_Imigration data'!A:G, 7, FALSE) -> 449288 | C35: =VLOOKUP(A35,'Raw_Imigration data'!A:H, 8, FALSE) -> 179715.2 | D35: ='Raw_Gross Domestic Product '!AI3 -> 16880.7 | E35: =((D35-D34)/D34)*100 -> 3.8556663 | F35: ='Raw_Personal Income and Its Dis'!AJ3 -> 14068.8 | G35: =Raw_Unemployment!B35 -> 88.3 | H35: =B34 -> 443126 | I35: =E34 -> 4.1943114 | K35: =B35 -> 449288 | L35: =G35 -> 88.3 | M35: =H35 -> 443126 | O35: =G35 -> 88.3 | P35: =E35 -> 3.8556663 | Q35: =B35 -> 449288 | R35: =H35 -> 443126 | T35: =F35 -> 14068.8 | U35: =B35 -> 449288 | V35: =D35 -> 16880.7 | W35: =G35 -> 88.3
A36: 2014 | B36: =VLOOKUP(A36,'Raw_Imigration data'!A:G, 7, FALSE) -> 517631 | C36: =VLOOKUP(A36,'Raw_Imigration data'!A:H, 8, FALSE) -> 207052.4 | D36: ='Raw_Gross Domestic Product '!AJ3 -> 17608.1 | E36: =((D36-D35)/D35)*100 -> 4.309063 | F36: ='Raw_Personal Income and Its Dis'!AK3 -> 14784.1 | G36: =Raw_Unemployment!B36 -> 73.9 | H36: =B35 -> 449288 | I36: =E35 -> 3.8556663 | K36: =B36 -> 517631 | L36: =G36 -> 73.9 | M36: =H36 -> 449288 | O36: =G36 -> 73.9 | P36: =E36 -> 4.309063 | Q36: =B36 -> 517631 | R36: =H36 -> 449288 | T36: =F36 -> 14784.1 | U36: =B36 -> 517631 | V36: =D36 -> 17608.1 | W36: =G36 -> 73.9
A37: 2015 | B37: =VLOOKUP(A37,'Raw_Imigration data'!A:G, 7, FALSE) -> 667012 | C37: =VLOOKUP(A37,'Raw_Imigration data'!A:H, 8, FALSE) -> 266804.8 | D37: ='Raw_Gross Domestic Product '!AK3 -> 18295 | E37: =((D37-D36)/D36)*100 -> 3.9010455 | F37: ='Raw_Personal Income and Its Dis'!AL3 -> 15473.7 | G37: =Raw_Unemployment!B37 -> 63.3 | H37: =B36 -> 517631 | I37: =E36 -> 4.309063 | K37: =B37 -> 667012 | L37: =G37 -> 63.3 | M37: =H37 -> 517631 | O37: =G37 -> 63.3 | P37: =E37 -> 3.9010455 | Q37: =B37 -> 667012 | R37: =H37 -> 517631 | T37: =F37 -> 15473.7 | U37: =B37 -> 667012 | V37: =D37 -> 18295 | W37: =G37 -> 63.3
A38: 2016 | B38: =VLOOKUP(A38,'Raw_Imigration data'!A:G, 7, FALSE) -> 829752 | C38: =VLOOKUP(A38,'Raw_Imigration data'!A:H, 8, FALSE) -> 331900.8 | D38: ='Raw_Gross Domestic Product '!AL3 -> 18804.9 | E38: =((D38-D37)/D37)*100 -> 2.7871003 | F38: ='Raw_Personal Income and Its Dis'!AM3 -> 15887.7 | G38: =Raw_Unemployment!B38 -> 58.5 | H38: =B37 -> 667012 | I38: =E37 -> 3.9010455 | K38: =B38 -> 829752 | L38: =G38 -> 58.5 | M38: =H38 -> 667012 | O38: =G38 -> 58.5 | P38: =E38 -> 2.7871003 | Q38: =B38 -> 829752 | R38: =H38 -> 667012 | T38: =F38 -> 15887.7 | U38: =B38 -> 829752 | V38: =D38 -> 18804.9 | W38: =G38 -> 58.5
A39: 2017 | B39: =VLOOKUP(A39,'Raw_Imigration data'!A:G, 7, FALSE) -> 796106 | C39: =VLOOKUP(A39,'Raw_Imigration data'!A:H, 8, FALSE) -> 318442.4 | D39: ='Raw_Gross Domestic Product '!AM3 -> 19612.1 | E39: =((D39-D38)/D38)*100 -> 4.2924982 | F39: ='Raw_Personal Income and Its Dis'!AN3 -> 16662.8 | G39: =Raw_Unemployment!B39 -> 52.3 | H39: =B38 -> 829752 | I39: =E38 -> 2.7871003 | K39: =B39 -> 796106 | L39: =G39 -> 52.3 | M39: =H39 -> 829752 | O39: =G39 -> 52.3 | P39: =E39 -> 4.2924982 | Q39: =B39 -> 796106 | R39: =H39 -> 829752 | T39: =F39 -> 16662.8 | U39: =B39 -> 796106 | V39: =D39 -> 19612.1 | W39: =G39 -> 52.3
A40: 2018 | B40: =VLOOKUP(A40,'Raw_Imigration data'!A:G, 7, FALSE) -> 631502 | C40: =VLOOKUP(A40,'Raw_Imigration data'!A:H, 8, FALSE) -> 252600.8 | D40: ='Raw_Gross Domestic Product '!AN3 -> 20656.5 | E40: =((D40-D39)/D39)*100 -> 5.3252839 | F40: ='Raw_Personal Income and Its Dis'!AO3 -> 17528.2 | G40: =Raw_Unemployment!B40 -> 46.7 | H40: =B39 -> 796106 | I40: =E39 -> 4.2924982 | K40: =B40 -> 631502 | L40: =G40 -> 46.7 | M40: =H40 -> 796106 | O40: =G40 -> 46.7 | P40: =E40 -> 5.3252839 | Q40: =B40 -> 631502 | R40: =H40 -> 796106 | T40: =F40 -> 17528.2 | U40: =B40 -> 631502 | V40: =D40 -> 20656.5 | W40: =G40 -> 46.7
A41: 2019 | B41: =VLOOKUP(A41,'Raw_Imigration data'!A:G, 7, FALSE) -> 543373 | C41: =VLOOKUP(A41,'Raw_Imigration data'!A:H, 8, FALSE) -> 217349.2 | D41: ='Raw_Gross Domestic Product '!AO3 -> 21540 | E41: =((D41-D40)/D40)*100 -> 4.2771041 | F41: ='Raw_Personal Income and Its Dis'!AP3 -> 18363.2 | G41: =Raw_Unemployment!B41 -> 44.1 | H41: =B40 -> 631502 | I41: =E40 -> 5.3252839 | K41: =B41 -> 543373 | L41: =G41 -> 44.1 | M41: =H41 -> 631502 | O41: =G41 -> 44.1 | P41: =E41 -> 4.2771041 | Q41: =B41 -> 543373 | R41: =H41 -> 631502 | T41: =F41 -> 18363.2 | U41: =B41 -> 543373 | V41: =D41 -> 21540 | W41: =G41 -> 44.1
A42: 2020 | B42: =VLOOKUP(A42,'Raw_Imigration data'!A:G, 7, FALSE) -> 313888 | C42: =VLOOKUP(A42,'Raw_Imigration data'!A:H, 8, FALSE) -> 125555.2 | D42: ='Raw_Gross Domestic Product '!AP3 -> 21375.3 | E42: =((D42-D41)/D41)*100 -> -0.76462396 | F42: ='Raw_Personal Income and Its Dis'!AQ3 -> 19631.7 | G42: =Raw_Unemployment!B42 -> 97.2 | H42: =B41 -> 543373 | I42: =E41 -> 4.2771041 | K42: =B42 -> 313888 | L42: =G42 -> 97.2 | M42: =H42 -> 543373 | O42: =G42 -> 97.2 | P42: =E42 -> -0.76462396 | Q42: =B42 -> 313888 | R42: =H42 -> 543373 | T42: =F42 -> 19631.7 | U42: =B42 -> 313888 | V42: =D42 -> 21375.3 | W42: =G42 -> 97.2
A43: 2021 | B43: =VLOOKUP(A43,'Raw_Imigration data'!A:G, 7, FALSE) -> 484038 | C43: =VLOOKUP(A43,'Raw_Imigration data'!A:H, 8, FALSE) -> 193615.2 | D43: ='Raw_Gross Domestic Product '!AQ3 -> 23725.6 | E43: =((D43-D42)/D42)*100 -> 10.995401 | F43: ='Raw_Personal Income and Its Dis'!AR3 -> 21498.9 | G43: =Raw_Unemployment!B43 -> 64.3 | H43: =B42 -> 313888 | I43: =E42 -> -0.76462396 | K43: =B43 -> 484038 | L43: =G43 -> 64.3 | M43: =H43 -> 313888 | O43: =G43 -> 64.3 | P43: =E43 -> 10.995401 | Q43: =B43 -> 484038 | R43: =H43 -> 313888 | T43: =F43 -> 21498.9 | U43: =B43 -> 484038 | V43: =D43 -> 23725.6 | W43: =G43 -> 64.3

Sheet Analysis
B1: Mean | C1: Median | D1: Std. Dev | E1: Min | F1: Max | G1: Count | J1: ='Master Dataset'!B1 -> Net Immigration | K1: ='Master Dataset'!D1 -> GDP Nominal | L1: ='Master Dataset'!E1 -> GDP Growth Rate | M1: ='Master Dataset'!F1 -> Personal Income | N1: ='Master Dataset'!G1 -> Unemployment Rate
A2: Net Immigration | B2: =AVERAGE('Master Dataset'!B2:B43) -> -38371.262 | C2: =MEDIAN('Master Dataset'!B2:B43) -> -89065.5 | D2: =_xlfn.STDEV.S('Master Dataset'!B2:B43) -> 525505.05 | E2: =MIN('Master Dataset'!B2:B43) -> -1027905 | F2: =MAX('Master Dataset'!B2:B43) -> 845690 | G2: =COUNT('Master Dataset'!B2:B43) -> 42 | J2: ='Master Dataset'!B2 -> -5813 | K2: ='Master Dataset'!D2 -> 2857.3 | M2: ='Master Dataset'!F2 -> 2324.5 | N2: ='Master Dataset'!G2 -> 86.1
A3: GDP growth rate | B3: =AVERAGE('Master Dataset'!E2:E43) -> 5.3313412 | C3: =MEDIAN('Master Dataset'!E2:E43) -> 5.3252839 | D3: =_xlfn.STDEV.S('Master Dataset'!E2:E43) -> 2.6750046 | E3: =MIN('Master Dataset'!E2:E43) -> -1.9756396 | F3: =MAX('Master Dataset'!E2:E43) -> 12.238827 | G3: =COUNT('Master Dataset'!E2:E43) -> 41 | J3: ='Master Dataset'!B3 -> -86988 | K3: ='Master Dataset'!D3 -> 3207 | L3: ='Master Dataset'!E3 -> 12.238827 | M3: ='Master Dataset'!F3 -> 2603.2 | N3: ='Master Dataset'!G3 -> 91.4
A4: Unemployment Rate | B4: =AVERAGE('Master Dataset'!G2:G43) -> 74.695238 | C4: =MEDIAN('Master Dataset'!G2:G43) -> 69.5 | D4: =_xlfn.STDEV.S('Master Dataset'!G2:G43) -> 19.971369 | E4: =MIN('Master Dataset'!G2:G43) -> 44.1 | F4: =MAX('Master Dataset'!G2:G43) -> 116.5 | G4: =COUNT('Master Dataset'!G2:G43) -> 42 | J4: ='Master Dataset'!B4 -> -196068 | K4: ='Master Dataset'!D4 -> 3343.8 | L4: ='Master Dataset'!E4 -> 4.2656688 | M4: ='Master Dataset'!F4 -> 2789.5 | N4: ='Master Dataset'!G4 -> 116.5
A5: Personal Income | B5: =AVERAGE('Master Dataset'!F2:F43) -> 9402.6524 | C5: =MEDIAN('Master Dataset'!F2:F43) -> 8807.2 | D5: =_xlfn.STDEV.S('Master Dataset'!F2:F43) -> 5242.6848 | E5: =MIN('Master Dataset'!F2:F43) -> 2324.5 | F5: =MAX('Master Dataset'!F2:F43) -> 21498.9 | G5: =COUNT('Master Dataset'!F2:F43) -> 42 | J5: ='Master Dataset'!B5 -> -339541 | K5: ='Master Dataset'!D5 -> 3634 | L5: ='Master Dataset'!E5 -> 8.6787487 | M5: ='Master Dataset'!F5 -> 2981.7 | N5: ='Master Dataset'!G5 -> 115.2
J6: ='Master Dataset'!B6 -> -316325 | K6: ='Master Dataset'!D6 -> 4037.6 | L6: ='Master Dataset'!E6 -> 11.106219 | M6: ='Master Dataset'!F6 -> 3288.7 | N6: ='Master Dataset'!G6 -> 90.1
J7: ='Master Dataset'!B7 -> -428548 | K7: ='Master Dataset'!D7 -> 4339 | L7: ='Master Dataset'!E7 -> 7.4648306 | M7: ='Master Dataset'!F7 -> 3522.9 | N7: ='Master Dataset'!G7 -> 86.3
J8: ='Master Dataset'!B8 -> -948739 | K8: ='Master Dataset'!D8 -> 4579.6 | L8: ='Master Dataset'!E8 -> 5.5450565 | M8: ='Master Dataset'!F8 -> 3731.2 | N8: ='Master Dataset'!G8 -> 84
J9: ='Master Dataset'!B9 -> -451122 | K9: ='Master Dataset'!D9 -> 4855.2 | L9: ='Master Dataset'!E9 -> 6.0179928 | M9: ='Master Dataset'!F9 -> 3946.8 | N9: ='Master Dataset'!G9 -> 74.1
B10: -5813 | C10: -2325.2 | D10: 2857.3 | F10: 2324.5 | G10: 86.1 | J10: ='Master Dataset'!B10 -> -219790 | K10: ='Master Dataset'!D10 -> 5236.4 | L10: ='Master Dataset'!E10 -> 7.8513758 | M10: ='Master Dataset'!F10 -> 4280 | N10: ='Master Dataset'!G10 -> 65.9
A11: -5813 | B11: 1 | J11: ='Master Dataset'!B11 -> 331925 | K11: ='Master Dataset'!D11 -> 5641.6 | L11: ='Master Dataset'!E11 -> 7.7381407 | M11: ='Master Dataset'!F11 -> 4621 | N11: ='Master Dataset'!G11 -> 63.1
A12: -2325.2 | B12: 1 | C12: 1 | J12: ='Master Dataset'!B12 -> 605366 | K12: ='Master Dataset'!D12 -> 5963.1 | L12: ='Master Dataset'!E12 -> 5.6987379 | M12: ='Master Dataset'!F12 -> 4913.3 | N12: ='Master Dataset'!G12 -> 67.4
A13: 2857.3 | B13: 0.58413019 | C13: 0.58413019 | D13: 1 | J13: ='Master Dataset'!B13 -> 845690 | K13: ='Master Dataset'!D13 -> 6158.1 | L13: ='Master Dataset'!E13 -> 3.2701112 | M13: ='Master Dataset'!F13 -> 5089.9 | N13: ='Master Dataset'!G13 -> 82.2
B14: -0.2935209 | C14: -0.2935209 | D14: -0.42512003 | E14: 1 | J14: ='Master Dataset'!B14 -> -60507 | K14: ='Master Dataset'!D14 -> 6520.3 | L14: ='Master Dataset'!E14 -> 5.8816843 | M14: ='Master Dataset'!F14 -> 5417.5 | N14: ='Master Dataset'!G14 -> 89.9
A15: 2324.5 | B15: 0.583286 | C15: 0.583286 | D15: 0.9980378 | E15: -0.41624809 | F15: 1 | J15: ='Master Dataset'!B15 -> -267855 | K15: ='Master Dataset'!D15 -> 6858.6 | L15: ='Master Dataset'!E15 -> 5.1884116 | M15: ='Master Dataset'!F15 -> 5652.9 | N15: ='Master Dataset'!G15 -> 82.9
A16: 86.1 | B16: 0.097272345 | C16: 0.097272345 | D16: -0.25610821 | E16: -0.13208492 | F16: -0.239667 | G16: 1 | J16: ='Master Dataset'!B16 -> -159108 | K16: ='Master Dataset'!D16 -> 7287.2 | L16: ='Master Dataset'!E16 -> 6.2490887 | M16: ='Master Dataset'!F16 -> 5940.9 | N16: ='Master Dataset'!G16 -> 73.2
J17: ='Master Dataset'!B17 -> -545538 | K17: ='Master Dataset'!D17 -> 7639.7 | L17: ='Master Dataset'!E17 -> 4.8372489 | M17: ='Master Dataset'!F17 -> 6283.4 | N17: ='Master Dataset'!G17 -> 67.1
J18: ='Master Dataset'!B18 -> -652127 | K18: ='Master Dataset'!D18 -> 8073.1 | L18: ='Master Dataset'!E18 -> 5.6729976 | M18: ='Master Dataset'!F18 -> 6666.2 | N18: ='Master Dataset'!G18 -> 64.9
J19: ='Master Dataset'!B19 -> -687616 | K19: ='Master Dataset'!D19 -> 8577.6 | L19: ='Master Dataset'!E19 -> 6.2491484 | M19: ='Master Dataset'!F19 -> 7074 | N19: ='Master Dataset'!G19 -> 59.3
A20: Correlation of Immigration and Economic Variables (1980–2021) | J20: ='Master Dataset'!B20 -> -1015022 | K20: ='Master Dataset'!D20 -> 9062.8 | L20: ='Master Dataset'!E20 -> 5.6565939 | M20: ='Master Dataset'!F20 -> 7588.4 | N20: ='Master Dataset'!G20 -> 54
B21: Net Immigration | C21: GDP Nominal | D21: GDP Growth Rate | E21: Personal Income | F21: Unemployment Rate | J21: ='Master Dataset'!B21 -> -1027905 | K21: ='Master Dataset'!D21 -> 9631.2 | L21: ='Master Dataset'!E21 -> 6.2717924 | M21: ='Master Dataset'!F21 -> 7978.6 | N21: ='Master Dataset'!G21 -> 50.6
A22: Net Immigration | B22: 1 | J22: ='Master Dataset'!B22 -> -951176 | K22: ='Master Dataset'!D22 -> 10251 | L22: ='Master Dataset'!E22 -> 6.4353352 | M22: ='Master Dataset'!F22 -> 8621.3 | N22: ='Master Dataset'!G22 -> 47.6
A23: GDP Nominal | B23: 0.5676538 | C23: 1 | J23: ='Master Dataset'!B23 -> -410575 | K23: ='Master Dataset'!D23 -> 10581.9 | L23: ='Master Dataset'!E23 -> 3.2279778 | M23: ='Master Dataset'!F23 -> 8993.1 | N23: ='Master Dataset'!G23 -> 56.9
A24: GDP Growth Rate | B24: -0.2935209 | C24: -0.42512003 | D24: 1 | J24: ='Master Dataset'!B24 -> -91143 | K24: ='Master Dataset'!D24 -> 10929.1 | L24: ='Master Dataset'!E24 -> 3.2810743 | M24: ='Master Dataset'!F24 -> 9150 | N24: ='Master Dataset'!G24 -> 69.4
A25: Personal Income | B25: 0.56773192 | C25: 0.99810792 | D25: -0.41624809 | E25: 1 | J25: ='Master Dataset'!B25 -> -424564 | K25: ='Master Dataset'!D25 -> 11456.5 | L25: ='Master Dataset'!E25 -> 4.825649 | M25: ='Master Dataset'!F25 -> 9481.8 | N25: ='Master Dataset'!G25 -> 71.9
A26: Unemployment Rate | B26: 0.097754597 | C26: -0.26866807 | D26: -0.13208492 | E26: -0.25245319 | F26: 1 | J26: ='Master Dataset'!B26 -> -396518 | K26: ='Master Dataset'!D26 -> 12217.2 | L26: ='Master Dataset'!E26 -> 6.6398987 | M26: ='Master Dataset'!F26 -> 10015.9 | N26: ='Master Dataset'!G26 -> 66.5
J27: ='Master Dataset'!B27 -> -167356 | K27: ='Master Dataset'!D27 -> 13039.2 | L27: ='Master Dataset'!E27 -> 6.7282192 | M27: ='Master Dataset'!F27 -> 10546.1 | N27: ='Master Dataset'!G27 -> 61
J28: ='Master Dataset'!B28 -> -17132 | K28: ='Master Dataset'!D28 -> 13815.6 | L28: ='Master Dataset'!E28 -> 5.954353 | M28: ='Master Dataset'!F28 -> 11302 | N28: ='Master Dataset'!G28 -> 55.3
J29: ='Master Dataset'!B29 -> -110139 | K29: ='Master Dataset'!D29 -> 14474.2 | L29: ='Master Dataset'!E29 -> 4.7670749 | M29: ='Master Dataset'!F29 -> 11932.1 | N29: ='Master Dataset'!G29 -> 55.4
J30: ='Master Dataset'!B30 -> -3825 | K30: ='Master Dataset'!D30 -> 14769.9 | L30: ='Master Dataset'!E30 -> 2.0429454 | M30: ='Master Dataset'!F30 -> 12425.7 | N30: ='Master Dataset'!G30 -> 69.6
J31: ='Master Dataset'!B31 -> 243114 | K31: ='Master Dataset'!D31 -> 14478.1 | L31: ='Master Dataset'!E31 -> -1.9756396 | M31: ='Master Dataset'!F31 -> 12065.7 | N31: ='Master Dataset'!G31 -> 111.4
J32: ='Master Dataset'!B32 -> 261671 | K32: ='Master Dataset'!D32 -> 15049 | L32: ='Master Dataset'!E32 -> 3.943197 | M32: ='Master Dataset'!F32 -> 12556.6 | N32: ='Master Dataset'!G32 -> 115.3
J33: ='Master Dataset'!B33 -> 405965 | K33: ='Master Dataset'!D33 -> 15599.7 | L33: ='Master Dataset'!E33 -> 3.6593794 | M33: ='Master Dataset'!F33 -> 13309.6 | N33: ='Master Dataset'!G33 -> 107.2
J34: ='Master Dataset'!B34 -> 443126 | K34: ='Master Dataset'!D34 -> 16254 | L34: ='Master Dataset'!E34 -> 4.1943114 | M34: ='Master Dataset'!F34 -> 13917.8 | N34: ='Master Dataset'!G34 -> 96.9
J35: ='Master Dataset'!B35 -> 449288 | K35: ='Master Dataset'!D35 -> 16880.7 | L35: ='Master Dataset'!E35 -> 3.8556663 | M35: ='Master Dataset'!F35 -> 14068.8 | N35: ='Master Dataset'!G35 -> 88.3
J36: ='Master Dataset'!B36 -> 517631 | K36: ='Master Dataset'!D36 -> 17608.1 | L36: ='Master Dataset'!E36 -> 4.309063 | M36: ='Master Dataset'!F36 -> 14784.1 | N36: ='Master Dataset'!G36 -> 73.9
J37: ='Master Dataset'!B37 -> 667012 | K37: ='Master Dataset'!D37 -> 18295 | L37: ='Master Dataset'!E37 -> 3.9010455 | M37: ='Master Dataset'!F37 -> 15473.7 | N37: ='Master Dataset'!G37 -> 63.3
J38: ='Master Dataset'!B38 -> 829752 | K38: ='Master Dataset'!D38 -> 18804.9 | L38: ='Master Dataset'!E38 -> 2.7871003 | M38: ='Master Dataset'!F38 -> 15887.7 | N38: ='Master Dataset'!G38 -> 58.5
... J43: ='Master Dataset'!B43 -> 484038 | K43: ='Master Dataset'!D43 -> 23725.6 | L43: ='Master Dataset'!E43 -> 10.995401 | M43: ='Master Dataset'!F43 -> 21498.9 | N43: ='Master Dataset'!G43 -> 64.3

Sheet Result 1
A1: SUMMARY OUTPUT | B1: MODEL 1: Impact of Immigration on GDP Growth
A3: Regression Statistics
A4: Multiple R | B4: 0.3101011
A5: R Square | B5: 0.096162692
A6: Adjusted R Square | B6: 0.024807115
A7: Standard Error | B7: 2.7327449
A8: Observations | B8: 42
A10: ANOVA
B11: df | C11: SS | D11: MS | E11: F | F11: Significance F
A12: Regression | B12: 3 | C12: 30.192435 | D12: 10.064145 | E12: 1.3476549 | F12: 0.27340928
A13: Residual | B13: 38 | C13: 283.78 | D13: 7.4678949
A14: Total | B14: 41 | C14: 313.97244
B16: Coefficients | C16: Standard Error | D16: t Stat | E16: P-value | F16: Lower 95% | G16: Upper 95% | H16: Lower 95.0% | I16: Upper 95.0%
A17: Intercept | B17: 6.4154939 | C17: 1.6984086 | D17: 3.7773559 | E17: 0.00054339677 | F17: 2.9772453 | G17: 9.8537424 | H17: 2.9772453 | I17: 9.8537424
A18: Net Immigration | B18: -1.2754859e-06 | C18: 1.6204676e-06 | D18: -0.78710982 | E18: 0.43609947 | F18: -4.5559511e-06 | G18: 2.0049792e-06 | H18: -4.5559511e-06 | I18: 2.0049792e-06
A19: Unemployment Rate | B19: -0.016988417 | C19: 0.021901711 | D19: -0.77566621 | E19: 0.44274692 | F19: -0.061326114 | G19: 0.027349279 | H19: -0.061326114 | I19: 0.027349279
A20: Immigration Lag1 | B20: -1.7882237e-07 | C20: 1.6609667e-06 | D20: -0.10766162 | E20: 0.91483056 | F20: -3.5412738e-06 | G20: 3.183629e-06 | H20: -3.5412738e-06 | I20: 3.183629e-06
A24: RESIDUAL OUTPUT
A26: Observation | B26: Predicted GDP Growth Rate | C26: Residuals
A27: 1 | B27: 4.9602055 | C27: -4.9602055
A28: 2 | B28: 4.974744 | C28: 7.2640829
A29: 3 | B29: 4.7019806 | C29: -0.43631176
A30: 4 | B30: 4.9265693 | C30: 3.7521794
A31: 5 | B31: 5.3490231 | C31: 5.757196
A32: 6 | B32: 5.5525664 | C32: 1.9122642
A33: 7 | B33: 6.275204 | C33: -0.73014756
A34: 8 | B34: 5.9017077 | C34: 0.11628518
A35: 9 | B35: 5.6569669 | C35: 2.1944089
A36: 10 | B36: 4.9594624 | C36: 2.7786783
A37: 11 | B37: 4.4389831 | C37: 1.2597549
A38: 12 | B38: 3.8321273 | C38: -0.56201608
... A68: 42 | B68: 4.6496248 | C68: 6.3457765

Sheet Result 2
A2: SUMMARY OUTPUT | B2: MODEL 2: Immigration Impact on Unemployment
A4: Regression Statistics
A5: Multiple R | B5: 0.2506513
A6: R Square | B6: 0.062826072
A7: Adjusted R Square | B7: -0.011161343
A8: Standard Error | B8: 20.082514
A9: Observations | B9: 42
A11: ANOVA
B12: df | C12: SS | D12: MS | E12: F | F12: Significance F
A13: Regression | B13: 3 | C13: 1027.3997 | D13: 342.46657 | E13: 0.84914538 | F13: 0.47572504
A14: Residual | B14: 38 | C14: 15325.679 | D14: 403.30735
A15: Total | B15: 41 | C15: 16353.079
B17: Coefficients | C17: Standard Error | D17: t Stat | E17: P-value | F17: Lower 95% | G17: Upper 95% | H17: Lower 95.0% | I17: Upper 95.0%
A18: Intercept | B18: 79.81005 | C18: 6.8305221 | D18: 11.684326 | E18: 3.8036925e-14 | F18: 65.982381 | G18: 93.637719 | H18: 65.982381 | I18: 93.637719
A19: GDP Growth Rate | B19: -0.91746787 | C19: 1.1828127 | D19: -0.77566621 | E19: 0.44274692 | F19: -3.3119471 | G19: 1.4770113 | H19: -3.3119471 | I19: 1.4770113
A20: Net Immigration | B20: -1.005021e-05 | C20: 1.1894027e-05 | D20: -0.84497965 | E20: 0.40341113 | F20: -3.4128409e-05 | G20: 1.4027988e-05 | H20: -3.4128409e-05 | I20: 1.4027988e-05
A21: Immigration Lag1 | B21: 1.45418e-05 | C21: 1.197796e-05 | D21: 1.2140465 | E21: 0.23222144 | F21: -9.7063122e-06 | G21: 3.8789913e-05 | H21: -9.7063122e-06 | I21: 3.8789913e-05
A25: RESIDUAL OUTPUT
A27: Observation | B27: Predicted Unemployment Rate | C27: Residuals
A28: 1 | B28: 79.868472 | C28: 6.231528
A29: 2 | B29: 69.371036 | C29: 22.028964
A30: 3 | B30: 76.601999 | C30: 39.898001
A31: 4 | B31: 72.408854 | C31: 42.791146
A32: 5 | B32: 67.862046 | C32: 22.237954
A33: 6 | B33: 72.66837 | C33: 13.63163
A34: 7 | B34: 78.025806 | C34: 5.9741939
A35: 8 | B35: 65.026233 | C35: 9.0737672
A36: 9 | B36: 68.255475 | C36: -2.3554747
A37: 10 | B37: 66.178496 | C37: -3.0784962
A38: 11 | B38: 73.324372 | C38: -5.9243725
A39: 12 | B39: 77.113577 | C39: 5.0864228
... A69: 42 | B69: 69.421936 | C69: -5.1219356

Sheet Result 3
A1: SUMMARY OUTPUT | B1: MODEL 3: Immigration Impact on Personal Income
A3: Regression Statistics
A4: Multiple R | B4: 0.99824891
A5: R Square | B5: 0.99650089
A6: Adjusted R Square | B6: 0.99622465
A7: Standard Error | B7: 322.13093
A8: Observations | B8: 42
A10: ANOVA
B11: df | C11: SS | D11: MS | E11: F | F11: Significance F
A12: Regression | B12: 3 | C12: 1.1229723e+09 | D12: 3.743241e+08 | E12: 3607.3056 | F12: 1.0832231e-46
A13: Residual | B13: 38 | C13: 3943196.8 | D13: 103768.34
A14: Total | B14: 41 | C14: 1.1269155e+09
B16: Coefficients | C16: Standard Error | D16: t Stat | E16: P-value | F16: Lower 95% | G16: Upper 95% | H16: Lower 95.0% | I16: Upper 95.0%
A17: Intercept | B17: -817.0173 | C17: 286.25944 | D17: -2.8541147 | E17: 0.0069509568 | F17: -1396.5192 | G17: -237.51535 | H17: -1396.5192 | I17: -237.51535
A18: Net Immigration | B18: -5.0423896e-05 | C18: 0.00012254759 | D18: -0.41146379 | E18: 0.68304405 | F18: -0.00029850852 | G18: 0.00019766073 | H18: -0.00029850852 | I18: 0.00019766073
A19: GDP Nominal | B19: 0.88305796 | C19: 0.011141656 | D19: 79.257338 | E19: 8.1857315e-44 | F19: 0.86050286 | G19: 0.90561307 | H19: 0.86050286 | I19: 0.90561307
A20: Unemployment Rate | B20: 4.8017817 | C20: 2.756027 | D20: 1.742284 | E20: 0.089548122 | F20: -0.77750319 | G20: 10.381067 | H20: -0.77750319 | I20: 10.381067
A24: RESIDUAL OUTPUT
A26: Observation | B26: Predicted Personal Income | C26: Residuals
A27: 1 | B27: 2119.8707 | C27: 204.62926
A28: 2 | B28: 2458.2187 | C28: 144.98129
A29: 3 | B29: 2705.046 | C29: 84.454003
A30: 4 | B30: 2962.3016 | C30: 19.398431
A31: 5 | B31: 3197.0084 | C31: 91.691598
A32: 6 | B32: 3450.574 | C32: 72.325978
A33: 7 | B33: 3678.2237 | C33: 52.976273
A34: 8 | B34: 3848.9651 | C34: 97.834925
A35: 9 | B35: 4134.5475 | C35: 145.4525
A36: 10 | B36: 4451.098 | C36: 169.90202
A37: 11 | B37: 4741.8608 | C37: 171.43919
A38: 12 | B38: 4973.0054 | C38: 116.89459
... A68: 42 | B68: 20418.41 | C68: 1080.4898

Sheet Training Data
A1: Year | B1: Net Immigration | C1: Immigration Rate | D1: GDP Nominal | E1: GDP Growth Rate | F1: Personal Income | G1: Unemployment Rate | H1: Immigration Lag1 | I1: GDP lag1 | K1: Net Immigration | L1: =G1 -> Unemployment Rate | M1: =H1 -> Immigration Lag1 | Y1: =E1 -> GDP Growth Rate | Z1: =B1 -> Net Immigration | AA1: =H1 -> Immigration Lag1 | AD1: =B1 -> Net Immigration | AE1: =D1 -> GDP Nominal | AF1: =G1 -> Unemployment Rate
A2: 1980 | B2: =VLOOKUP(A2,'Raw_Imigration data'!A:G, 7, FALSE) -> -5813 | C2: =VLOOKUP(A2,'Raw_Imigration data'!A:H, 8, FALSE) -> -2325.2 | D2: ='Raw_Gross Domestic Product '!B3 -> 2857.3 | F2: ='Raw_Personal Income and Its Dis'!C3 -> 2324.5 | G2: =Raw_Unemployment!B2 -> 86.1 | K2: =B2 -> -5813 | L2: =G2 -> 86.1 | M2: =H2 -> 0 | O2: SUMMARY OUTPUT | P2: Model 1 | Y2: =E2 -> 0 | Z2: =B2 -> -5813 | AA2: =H2 -> 0 | AD2: =B2 -> -5813 | AE2: =D2 -> 2857.3 | AF2: =G2 -> 86.1
A3: 1981 | B3: =VLOOKUP(A3,'Raw_Imigration data'!A:G, 7, FALSE) -> -86988 | C3: =VLOOKUP(A3,'Raw_Imigration data'!A:H, 8, FALSE) -> -34795.2 | D3: ='Raw_Gross Domestic Product '!C3 -> 3207 | E3: =((D3-D2)/D2)*100 -> 12.238827 | F3: ='Raw_Personal Income and Its Dis'!D3 -> 2603.2 | G3: =Raw_Unemployment!B3 -> 91.4 | H3: =B2 -> -5813 | K3: =B3 -> -86988 | L3: =G3 -> 91.4 | M3: =H3 -> -5813 | Y3: =E3 -> 12.238827 | Z3: =B3 -> -86988 | AA3: =H3 -> -5813 | AD3: =B3 -> -86988 | AE3: =D3 -> 3207 | AF3: =G3 -> 91.4
A4: 1982 | B4: =VLOOKUP(A4,'Raw_Imigration data'!A:G, 7, FALSE) -> -196068 | C4: =VLOOKUP(A4,'Raw_Imigration data'!A:H, 8, FALSE) -> -78427.2 | D4: ='Raw_Gross Domestic Product '!D3 -> 3343.8 | E4: =((D4-D3)/D3)*100 -> 4.2656688 | F4: ='Raw_Personal Income and Its Dis'!E3 -> 2789.5 | G4: =Raw_Unemployment!B4 -> 116.5 | H4: =B3 -> -86988 | I4: =E3 -> 12.238827 | K4: =B4 -> -196068 | L4: =G4 -> 116.5 | M4: =H4 -> -86988 | O4: Regression Statistics | Y4: =E4 -> 4.2656688 | Z4: =B4 -> -196068 | AA4: =H4 -> -86988 | AD4: =B4 -> -196068 | AE4: =D4 -> 3343.8 | AF4: =G4 -> 116.5
A5: 1983 | B5: =VLOOKUP(A5,'Raw_Imigration data'!A:G, 7, FALSE) -> -339541 | C5: =VLOOKUP(A5,'Raw_Imigration data'!A:H, 8, FALSE) -> -135816.4 | D5: ='Raw_Gross Domestic Product '!E3 -> 3634 | E5: =((D5-D4)/D4)*100 -> 8.6787487 | F5: ='Raw_Personal Income and Its Dis'!F3 -> 2981.7 | G5: =Raw_Unemployment!B5 -> 115.2 | H5: =B4 -> -196068 | I5: =E4 -> 4.2656688 | K5: =B5 -> -339541 | L5: =G5 -> 115.2 | M5: =H5 -> -196068 | O5: Multiple R | P5: 0.45658094 | Y5: =E5 -> 8.6787487 | Z5: =B5 -> -339541 | AA5: =H5 -> -196068 | AD5: =B5 -> -339541 | AE5: =D5 -> 3634 | AF5: =G5 -> 115.2
A6: 1984 | B6: =VLOOKUP(A6,'Raw_Imigration data'!A:G, 7, FALSE) -> -316325 | C6: =VLOOKUP(A6,'Raw_Imigration data'!A:H, 8, FALSE) -> -126530 | D6: ='Raw_Gross Domestic Product '!F3 -> 4037.6 | E6: =((D6-D5)/D5)*100 -> 11.106219 | F6: ='Raw_Personal Income and Its Dis'!G3 -> 3288.7 | G6: =Raw_Unemployment!B6 -> 90.1 | H6: =B5 -> -339541 | I6: =E5 -> 8.6787487 | K6: =B6 -> -316325 | L6: =G6 -> 90.1 | M6: =H6 -> -339541 | O6: R Square | P6: 0.20846616 | Y6: =E6 -> 11.106219 | Z6: =B6 -> -316325 | AA6: =H6 -> -339541 | AD6: =B6 -> -316325 | AE6: =D6 -> 4037.6 | AF6: =G6 -> 90.1
A7: 1985 | B7: =VLOOKUP(A7,'Raw_Imigration data'!A:G, 7, FALSE) -> -428548 | C7: =VLOOKUP(A7,'Raw_Imigration data'!A:H, 8, FALSE) -> -171419.2 | D7: ='Raw_Gross Domestic Product '!G3 -> 4339 | E7: =((D7-D6)/D6)*100 -> 7.4648306 | F7: ='Raw_Personal Income and Its Dis'!H3 -> 3522.9 | G7: =Raw_Unemployment!B7 -> 86.3 | H7: =B6 -> -316325 | I7: =E6 -> 11.106219 | K7: =B7 -> -428548 | L7: =G7 -> 86.3 | M7: =H7 -> -316325 | O7: Adjusted R Square | P7: 0.13425986 | Y7: =E7 -> 7.4648306 | Z7: =B7 -> -428548 | AA7: =H7 -> -316325 | AD7: =B7 -> -428548 | AE7: =D7 -> 4339 | AF7: =G7 -> 86.3
A8: 1986 | B8: =VLOOKUP(A8,'Raw_Imigration data'!A:G, 7, FALSE) -> -948739 | C8: =VLOOKUP(A8,'Raw_Imigration data'!A:H, 8, FALSE) -> -379495.6 | D8: ='Raw_Gross Domestic Product '!H3 -> 4579.6 | E8: =((D8-D7)/D7)*100 -> 5.5450565 | F8: ='Raw_Personal Income and Its Dis'!I3 -> 3731.2 | G8: =Raw_Unemployment!B8 -> 84 | H8: =B7 -> -428548 | I8: =E7 -> 7.4648306 | K8: =B8 -> -948739 | L8: =G8 -> 84 | M8: =H8 -> -428548 | O8: Standard Error | P8: 6.3510312 | Y8: =E8 -> 5.5450565 | Z8: =B8 -> -948739 | AA8: =H8 -> -428548 | AD8: =B8 -> -948739 | AE8: =D8 -> 4579.6 | AF8: =G8 -> 84
A9: 1987 | B9: =VLOOKUP(A9,'Raw_Imigration data'!A:G, 7, FALSE) -> -451122 | C9: =VLOOKUP(A9,'Raw_Imigration data'!A:H, 8, FALSE) -> -180448.8 | D9: ='Raw_Gross Domestic Product '!I3 -> 4855.2 | E9: =((D9-D8)/D8)*100 -> 6.0179928 | F9: ='Raw_Personal Income and Its Dis'!J3 -> 3946.8 | G9: =Raw_Unemployment!B9 -> 74.1 | H9: =B8 -> -948739 | I9: =E8 -> 5.5450565 | K9: =B9 -> -451122 | L9: =G9 -> 74.1 | M9: =H9 -> -948739 | O9: Observations | P9: 36 | Y9: =E9 -> 6.0179928 | Z9: =B9 -> -451122 | AA9: =H9 -> -948739 | AD9: =B9 -> -451122 | AE9: =D9 -> 4855.2 | AF9: =G9 -> 74.1
A10: 1988 | B10: =VLOOKUP(A10,'Raw_Imigration data'!A:G, 7, FALSE) -> -219790 | C10: =VLOOKUP(A10,'Raw_Imigration data'!A:H, 8, FALSE) -> -87916 | D10: ='Raw_Gross Domestic Product '!J3 -> 5236.4 | E10: =((D10-D9)/D9)*100 -> 7.8513758 | F10: ='Raw_Personal Income and Its Dis'!K3 -> 4280 | G10: =Raw_Unemployment!B10 -> 65.9 | H10: =B9 -> -451122 | I10: =E9 -> 6.0179928 | K10: =B10 -> -219790 | L10: =G10 -> 65.9 | M10: =H10 -> -451122 | Y10: =E10 -> 7.8513758 | Z10: =B10 -> -219790 | AA10: =H10 -> -451122 | AD10: =B10 -> -219790 | AE10: =D10 -> 5236.4 | AF10: =G10 -> 65.9
A11: 1989 | B11: =VLOOKUP(A11,'Raw_Imigration data'!A:G, 7, FALSE) -> 331925 | C11: =VLOOKUP(A11,'Raw_Imigration data'!A:H, 8, FALSE) -> 132770 | D11: ='Raw_Gross Domestic Product '!K3 -> 5641.6 | E11: =((D11-D10)/D10)*100 -> 7.7381407 | F11: ='Raw_Personal Income and Its Dis'!L3 -> 4621 | G11: =Raw_Unemployment!B11 -> 63.1 | H11: =B10 -> -219790 | I11: =E10 -> 7.8513758 | K11: =B11 -> 331925 | L11: =G11 -> 63.1 | M11: =H11 -> -219790 | O11: ANOVA | Y11: =E11 -> 7.7381407 | Z11: =B11 -> 331925 | AA11: =H11 -> -219790 | AD11: =B11 -> 331925 | AE11: =D11 -> 5641.6 | AF11: =G11 -> 63.1
A12: 1990 | B12: =VLOOKUP(A12,'Raw_Imigration data'!A:G, 7, FALSE) -> 605366 | C12: =VLOOKUP(A12,'Raw_Imigration data'!A:H, 8, FALSE) -> 242146.4 | D12: ='Raw_Gross Domestic Product '!L3 -> 5963.1 | E12: =((D12-D11)/D11)*100 -> 5.6987379 | F12: ='Raw_Personal Income and Its Dis'!M3 -> 4913.3 | G12: =Raw_Unemployment!B12 -> 67.4 | H12: =B11 -> 331925 | I12: =E11 -> 7.7381407 | K12: =B12 -> 605366 | L12: =G12 -> 67.4 | M12: =H12 -> 331925 | P12: df | Q12: SS | R12: MS | S12: F | T12: Significance F | Y12: =E12 -> 5.6987379 | Z12: =B12 -> 605366 | AA12: =H12 -> 331925 | AD12: =B12 -> 605366 | AE12: =D12 -> 5963.1 | AF12: =G12 -> 67.4
A13: 1991 | B13: =VLOOKUP(A13,'Raw_Imigration data'!A:G, 7, FALSE) -> 845690 | C13: =VLOOKUP(A13,'Raw_Imigration data'!A:H, 8, FALSE) -> 338276 | D13: ='Raw_Gross Domestic Product '!M3 -> 6158.1 | E13: =((D13-D12)/D12)*100 -> 3.2701112 | F13: ='Raw_Personal Income and Its Dis'!N3 -> 5089.9 | G13: =Raw_Unemployment!B13 -> 82.2 | H13: =B12 -> 605366 | I13: =E12 -> 5.6987379 | K13: =B13 -> 845690 | L13: =G13 -> 82.2 | M13: =H13 -> 605366 | O13: Regression | P13: 3 | Q13: 339.94178 | R13: 113.31393 | S13: 2.8092785 | T13: 0.055187726 | Y13: =E13 -> 3.2701112 | Z13: =B13 -> 845690 | AA13: =H13 -> 605366 | AD13: =B13 -> 845690 | AE13: =D13 -> 6158.1 | AF13: =G13 -> 82.2
A14: 1992 | B14: =VLOOKUP(A14,'Raw_Imigration data'!A:G, 7, FALSE) -> -60507 | C14: =VLOOKUP(A14,'Raw_Imigration data'!A:H, 8, FALSE) -> -24202.8 | D14: ='Raw_Gross Domestic Product '!N3 -> 6520.3 | E14: =((D14-D13)/D13)*100 -> 5.8816843 | F14: ='Raw_Personal Income and Its Dis'!O3 -> 5417.5 | G14: =Raw_Unemployment!B14 -> 89.9 | H14: =B13 -> 845690 | I14: =E13 -> 3.2701112 | K14: =B14 -> -60507 | L14: =G14 -> 89.9 | M14: =H14 -> 845690 | O14: Residual | P14: 32 | Q14: 1290.7391 | R14: 40.335597 | Y14: =E14 -> 5.8816843 | Z14: =B14 -> -60507 | AA14: =H14 -> 845690 | AD14: =B14 -> -60507 | AE14: =D14 -> 6520.3 | AF14: =G14 -> 89.9
A15: 1993 | B15: =VLOOKUP(A15,'Raw_Imigration data'!A:G, 7, FALSE) -> -267855 | C15: =VLOOKUP(A15,'Raw_Imigration data'!A:H, 8, FALSE) -> -107142 | D15: ='Raw_Gross Domestic Product '!O3 -> 6858.6 | E15: =((D15-D14)/D14)*100 -> 5.1884116 | F15: ='Raw_Personal Income and Its Dis'!P3 -> 5652.9 | G15: =Raw_Unemployment!B15 -> 82.9 | H15: =B14 -> -60507 | I15: =E14 -> 5.8816843 | K15: =B15 -> -267855 | L15: =G15 -> 82.9 | M15: =H15 -> -60507 | O15: Total | P15: 35 | Q15: 1630.6809 | Y15: =E15 -> 5.1884116 | Z15: =B15 -> -267855 | AA15: =H15 -> -60507 | AD15: =B15 -> -267855 | AE15: =D15 -> 6858.6 | AF15: =G15 -> 82.9
A16: 1994 | B16: =VLOOKUP(A16,'Raw_Imigration data'!A:G, 7, FALSE) -> -159108 | C16: =VLOOKUP(A16,'Raw_Imigration data'!A:H, 8, FALSE) -> -63643.2 | D16: ='Raw_Gross Domestic Product '!P3 -> 7287.2 | E16: =((D16-D15)/D15)*100 -> 6.2490887 | F16: ='Raw_Personal Income and Its Dis'!Q3 -> 5940.9 | G16: =Raw_Unemployment!B16 -> 73.2 | H16: =B15 -> -267855 | I16: =E15 -> 5.1884116 | K16: =B16 -> -159108 | L16: =G16 -> 73.2 | M16: =H16 -> -267855 | Y16: =E16 -> 6.2490887 | Z16: =B16 -> -159108 | AA16: =H16 -> -267855 | AD16: =B16 -> -159108 | AE16: =D16 -> 7287.2 | AF16: =G16 -> 73.2
A17: 1995 | B17: =VLOOKUP(A17,'Raw_Imigration data'!A:G, 7, FALSE) -> -545538 | C17: =VLOOKUP(A17,'Raw_Imigration data'!A:H, 8, FALSE) -> -218215.2 | D17: ='Raw_Gross Domestic Product '!Q3 -> 7639.7 | E17: =((D17-D16)/D16)*100 -> 4.8372489 | F17: ='Raw_Personal Income and Its Dis'!R3 -> 6283.4 | G17: =Raw_Unemployment!B17 -> 67.1 | H17: =B16 -> -159108 | I17: =E16 -> 6.2490887 | K17: =B17 -> -545538 | L17: =G17 -> 67.1 | M17: =H17 -> -159108 | P17: Coefficients | Q17: Standard Error | R17: t Stat | S17: P-value | T17: Lower 95% | U17: Upper 95% | V17: Lower 95.0% | W17: Upper 95.0% | Y17: =E17 -> 4.8372489 | Z17: =B17 -> -545538 | AA17: =H17 -> -159108 | AD17: =B17 -> -545538 | AE17: =D17 -> 7639.7 | AF17: =G17 -> 67.1
A18: 1996 | B18: =VLOOKUP(A18,'Raw_Imigration data'!A:G, 7, FALSE) -> -652127 | C18: =VLOOKUP(A18,'Raw_Imigration data'!A:H, 8, FALSE) -> -260850.8 | D18: ='Raw_Gross Domestic Product '!R3 -> 8073.1 | E18: =((D18-D17)/D17)*100 -> 5.6729976 | F18: ='Raw_Personal Income and Its Dis'!S3 -> 6666.2 | G18: =Raw_Unemployment!B18 -> 64.9 | H18: =B17 -> -545538 | I18: =E17 -> 4.8372489 | K18: =B18 -> -652127 | L18: =G18 -> 64.9 | M18: =H18 -> -545538 | O18: Intercept | P18: -4.3144372 | Q18: 4.9093933 | R18: -0.87881269 | S18: 0.38605437 | T18: -14.314544 | U18: 5.6856698 | V18: -14.314544 | W18: 5.6856698 | Y18: =E18 -> 5.6729976 | Z18: =B18 -> -652127 | AA18: =H18 -> -545538 | AD18: =B18 -> -652127 | AE18: =D18 -> 8073.1 | AF18: =G18 -> 64.9
A19: 1997 | B19: =VLOOKUP(A19,'Raw_Imigration data'!A:G, 7, FALSE) -> -687616 | C19: =VLOOKUP(A19,'Raw_Imigration data'!A:H, 8, FALSE) -> -275046.4 | D19: ='Raw_Gross Domestic Product '!S3 -> 8577.6 | E19: =((D19-D18)/D18)*100 -> 6.2491484 | F19: ='Raw_Personal Income and Its Dis'!T3 -> 7074 | G19: =Raw_Unemployment!B19 -> 59.3 | H19: =B18 -> -652127 | I19: =E18 -> 5.6729976 | K19: =B19 -> -687616 | L19: =G19 -> 59.3 | M19: =H19 -> -652127 | O19: Net Immigration | P19: -2.4616384e-06 | Q19: 3.8442702e-06 | R19: -0.64033959 | S19: 0.52651081 | T19: -1.029216e-05 | U19: 5.3688837e-06 | V19: -1.029216e-05 | W19: 5.3688837e-06 | Y19: =E19 -> 6.2491484 | Z19: =B19 -> -687616 | AA19: =H19 -> -652127 | AD19: =B19 -> -687616 | AE19: =D19 -> 8577.6 | AF19: =G19 -> 59.3
A20: 1998 | B20: =VLOOKUP(A20,'Raw_Imigration data'!A:G, 7, FALSE) -> -1015022 | C20: =VLOOKUP(A20,'Raw_Imigration data'!A:H, 8, FALSE) -> -406008.8 | D20: ='Raw_Gross Domestic Product '!T3 -> 9062.8 | E20: =((D20-D19)/D19)*100 -> 5.6565939 | F20: ='Raw_Personal Income and Its Dis'!U3 -> 7588.4 | G20: =Raw_Unemployment!B20 -> 54 | H20: =B19 -> -687616 | I20: =E19 -> 6.2491484 | K20: =B20 -> -1015022 | L20: =G20 -> 54 | M20: =H20 -> -687616 | O20: Unemployment Rate | P20: 0.10181284 | Q20: 0.060788739 | R20: 1.6748635 | S20: 0.10370822 | T20: -0.022009767 | U20: 0.22563545 | V20: -0.022009767 | W20: 0.22563545 | Y20: =E20 -> 5.6565939 | Z20: =B20 -> -1015022 | AA20: =H20 -> -687616 | AD20: =B20 -> -1015022 | AE20: =D20 -> 9062.8 | AF20: =G20 -> 54
A21: 1999 | B21: =VLOOKUP(A21,'Raw_Imigration data'!A:G, 7, FALSE) -> -1027905 | C21: =VLOOKUP(A21,'Raw_Imigration data'!A:H, 8, FALSE) -> -411162 | D21: ='Raw_Gross Domestic Product '!U3 -> 9631.2 | E21: =((D21-D20)/D20)*100 -> 6.2717924 | F21: ='Raw_Personal Income and Its Dis'!V3 -> 7978.6 | G21: =Raw_Unemployment!B21 -> 50.6 | H21: =B20 -> -1015022 | I21: =E20 -> 5.6565939 | K21: =B21 -> -1027905 | L21: =G21 -> 50.6 | M21: =H21 -> -1015022 | O21: Immigration Lag 1 | P21: -4.4932102e-06 | Q21: 4.1835745e-06 | R21: -1.0740122 | S21: 0.29084946 | T21: -1.3014873e-05 | U21: 4.0284522e-06 | V21: -1.3014873e-05 | W21: 4.0284522e-06 | Y21: =E21 -> 6.2717924 | Z21: =B21 -> -1027905 | AA21: =H21 -> -1015022 | AD21: =B21 -> -1027905 | AE21: =D21 -> 9631.2 | AF21: =G21 -> 50.6
A22: 2000 | B22: =VLOOKUP(A22,'Raw_Imigration data'!A:G, 7, FALSE) -> -951176 | C22: =VLOOKUP(A22,'Raw_Imigration data'!A:H, 8, FALSE) -> -380470.4 | D22: ='Raw_Gross Domestic Product '!V3 -> 10251 | E22: =((D22-D21)/D21)*100 -> 6.4353352 | F22: ='Raw_Personal Income and Its Dis'!W3 -> 8621.3 | G22: =Raw_Unemployment!B22 -> 47.6 | H22: =B21 -> -1027905 | I22: =E21 -> 6.2717924 | K22: =B22 -> -951176 | L22: =G22 -> 47.6 | M22: =H22 -> -1027905 | Y22: =E22 -> 6.4353352 | Z22: =B22 -> -951176 | AA22: =H22 -> -1027905 | AD22: =B22 -> -951176 | AE22: =D22 -> 10251 | AF22: =G22 -> 47.6
A23: 2001 | B23: =VLOOKUP(A23,'Raw_Imigration data'!A:G, 7, FALSE) -> -410575 | C23: =VLOOKUP(A23,'Raw_Imigration data'!A:H, 8, FALSE) -> -164230 | D23: ='Raw_Gross Domestic Product '!W3 -> 10581.9 | E23: =((D23-D22)/D22)*100 -> 3.2279778 | F23: ='Raw_Personal Income and Its Dis'!X3 -> 8993.1 | G23: =Raw_Unemployment!B23 -> 56.9 | H23: =B22 -> -951176 | I23: =E22 -> 6.4353352 | K23: =B23 -> -410575 | L23: =G23 -> 56.9 | M23: =H23 -> -951176 | Y23: =E23 -> 3.2279778 | Z23: =B23 -> -410575 | AA23: =H23 -> -951176 | AD23: =B23 -> -410575 | AE23: =D23 -> 10581.9 | AF23: =G23 -> 56.9
A24: 2002 | B24: =VLOOKUP(A24,'Raw_Imigration data'!A:G, 7, FALSE) -> -91143 | C24: =VLOOKUP(A24,'Raw_Imigration data'!A:H, 8, FALSE) -> -36457.2 | D24: ='Raw_Gross Domestic Product '!X3 -> 10929.1 | E24: =((D24-D23)/D23)*100 -> 3.2810743 | F24: ='Raw_Personal Income and Its Dis'!Y3 -> 9150 | G24: =Raw_Unemployment!B24 -> 69.4 | H24: =B23 -> -410575 | I24: =E23 -> 3.2279778 | K24: =B24 -> -91143 | L24: =G24 -> 69.4 | M24: =H24 -> -410575 | Y24: =E24 -> 3.2810743 | Z24: =B24 -> -91143 | AA24: =H24 -> -410575 | AD24: =B24 -> -91143 | AE24: =D24 -> 10929.1 | AF24: =G24 -> 69.4
A25: 2003 | B25: =VLOOKUP(A25,'Raw_Imigration data'!A:G, 7, FALSE) -> -424564 | C25: =VLOOKUP(A25,'Raw_Imigration data'!A:H, 8, FALSE) -> -169825.6 | D25: ='Raw_Gross Domestic Product '!Y3 -> 11456.5 | E25: =((D25-D24)/D24)*100 -> 4.825649 | F25: ='Raw_Personal Income and Its Dis'!Z3 -> 9481.8 | G25: =Raw_Unemployment!B25 -> 71.9 | H25: =B24 -> -91143 | I25: =E24 -> 3.2810743 | K25: =B25 -> -424564 | L25: =G25 -> 71.9 | M25: =H25 -> -91143 | O25: SUMMARY OUTPUT | P25: Model 2 | Y25: =E25 -> 4.825649 | Z25: =B25 -> -424564 | AA25: =H25 -> -91143 | AD25: =B25 -> -424564 | AE25: =D25 -> 11456.5 | AF25: =G25 -> 71.9
A26: 2004 | B26: =VLOOKUP(A26,'Raw_Imigration data'!A:G, 7, FALSE) -> -396518 | C26: =VLOOKUP(A26,'Raw_Imigration data'!A:H, 8, FALSE) -> -158607.2 | D26: ='Raw_Gross Domestic Product '!Z3 -> 12217.2 | E26: =((D26-D25)/D25)*100 -> 6.6398987 | F26: ='Raw_Personal Income and Its Dis'!AA3 -> 10015.9 | G26: =Raw_Unemployment!B26 -> 66.5 | H26: =B25 -> -424564 | I26: =E25 -> 4.825649 | K26: =B26 -> -396518 | L26: =G26 -> 66.5 | M26: =H26 -> -424564 | Y26: =E26 -> 6.6398987 | Z26: =B26 -> -396518 | AA26: =H26 -> -424564 | AD26: =B26 -> -396518 | AE26: =D26 -> 12217.2 | AF26: =G26 -> 66.5
A27: 2005 | B27: =VLOOKUP(A27,'Raw_Imigration data'!A:G, 7, FALSE) -> -167356 | C27: =VLOOKUP(A27,'Raw_Imigration data'!A:H, 8, FALSE) -> -66942.4 | D27: ='Raw_Gross Domestic Product '!AA3 -> 13039.2 | E27: =((D27-D26)/D26)*100 -> 6.7282192 | F27: ='Raw_Personal Income and Its Dis'!AB3 -> 10546.1 | G27: =Raw_Unemployment!B27 -> 61 | H27: =B26 -> -396518 | I27: =E26 -> 6.6398987 | K27: =B27 -> -167356 | L27: =G27 -> 61 | M27: =H27 -> -396518 | O27: Regression Statistics | Y27: =E27 -> 6.7282192 | Z27: =B27 -> -167356 | AA27: =H27 -> -396518 | AD27: =B27 -> -167356 | AE27: =D27 -> 13039.2 | AF27: =G27 -> 61
A28: 2006 | B28: =VLOOKUP(A28,'Raw_Imigration data'!A:G, 7, FALSE) -> -17132 | C28: =VLOOKUP(A28,'Raw_Imigration data'!A:H, 8, FALSE) -> -6852.8 | D28: ='Raw_Gross Domestic Product '!AB3 -> 13815.6 | E28: =((D28-D27)/D27)*100 -> 5.954353 | F28: ='Raw_Personal Income and Its Dis'!AC3 -> 11302 | G28: =Raw_Unemployment!B28 -> 55.3 | H28: =B27 -> -167356 | I28: =E27 -> 6.7282192 | K28: =B28 -> -17132 | L28: =G28 -> 55.3 | M28: =H28 -> -167356 | O28: Multiple R | P28: 0.49275109 | Y28: =E28 -> 5.954353 | Z28: =B28 -> -17132 | AA28: =H28 -> -167356 | AD28: =B28 -> -17132 | AE28: =D28 -> 13815.6 | AF28: =G28 -> 55.3
A29: 2007 | B29: =VLOOKUP(A29,'Raw_Imigration data'!A:G, 7, FALSE) -> -110139 | C29: =VLOOKUP(A29,'Raw_Imigration data'!A:H, 8, FALSE) -> -44055.6 | D29: ='Raw_Gross Domestic Product '!AC3 -> 14474.2 | E29: =((D29-D28)/D28)*100 -> 4.7670749 | F29: ='Raw_Personal Income and Its Dis'!AD3 -> 11932.1 | G29: =Raw_Unemployment!B29 -> 55.4 | H29: =B28 -> -17132 | I29: =E28 -> 5.954353 | K29: =B29 -> -110139 | L29: =G29 -> 55.4 | M29: =H29 -> -17132 | O29: R Square | P29: 0.24280363 | Y29: =E29 -> 4.7670749 | Z29: =B29 -> -110139 | AA29: =H29 -> -17132 | AD29: =B29 -> -110139 | AE29: =D29 -> 14474.2 | AF29: =G29 -> 55.4
A30: 2008 | B30: =VLOOKUP(A30,'Raw_Imigration data'!A:G, 7, FALSE) -> -3825 | C30: =VLOOKUP(A30,'Raw_Imigration data'!A:H, 8, FALSE) -> -1530 | D30: ='Raw_Gross Domestic Product '!AD3 -> 14769.9 | E30: =((D30-D29)/D29)*100 -> 2.0429454 | F30: ='Raw_Personal Income and Its Dis'!AE3 -> 12425.7 | G30: =Raw_Unemployment!B30 -> 69.6 | H30: =B29 -> -110139 | I30: =E29 -> 4.7670749 | K30: =B30 -> -3825 | L30: =G30 -> 69.6 | M30: =H30 -> -110139 | O30: Adjusted R Square | P30: 0.1739676 | Y30: =E30 -> 2.0429454 | Z30: =B30 -> -3825 | AA30: =H30 -> -110139 | AD30: =B30 -> -3825 | AE30: =D30 -> 14769.9 | AF30: =G30 -> 69.6
A31: 2009 | B31: =VLOOKUP(A31,'Raw_Imigration data'!A:G, 7, FALSE) -> 243114 | C31: =VLOOKUP(A31,'Raw_Imigration data'!A:H, 8, FALSE) -> 97245.6 | D31: ='Raw_Gross Domestic Product '!AE3 -> 14478.1 | E31: =((D31-D30)/D30)*100 -> -1.9756396 | F31: ='Raw_Personal Income and Its Dis'!AF3 -> 12065.7 | G31: =Raw_Unemployment!B31 -> 111.4 | H31: =B30 -> -3825 | I31: =E30 -> 2.0429454 | K31: =B31 -> 243114 | L31: =G31 -> 111.4 | M31: =H31 -> -3825 | O31: Standard Error | P31: 17.52755 | Y31: =E31 -> -1.9756396 | Z31: =B31 -> 243114 | AA31: =H31 -> -3825 | AD31: =B31 -> 243114 | AE31: =D31 -> 14478.1 | AF31: =G31 -> 111.4
A32: 2010 | B32: =VLOOKUP(A32,'Raw_Imigration data'!A:G, 7, FALSE) -> 261671 | C32: =VLOOKUP(A32,'Raw_Imigration data'!A:H, 8, FALSE) -> 104668.4 | D32: ='Raw_Gross Domestic Product '!AF3 -> 15049 | E32: =((D32-D31)/D31)*100 -> 3.943197 | F32: ='Raw_Personal Income and Its Dis'!AG3 -> 12556.6 | G32: =Raw_Unemployment!B32 -> 115.3 | H32: =B31 -> 243114 | I32: =E31 -> -1.9756396 | K32: =B32 -> 261671 | L32: =G32 -> 115.3 | M32: =H32 -> 243114 | O32: Observations | P32: 37 | Y32: =E32 -> 3.943197 | Z32: =B32 -> 261671 | AA32: =H32 -> 243114 | AD32: =B32 -> 261671 | AE32: =D32 -> 15049 | AF32: =G32 -> 115.3
A33: 2011 | B33: =VLOOKUP(A33,'Raw_Imigration data'!A:G, 7, FALSE) -> 405965 | C33: =VLOOKUP(A33,'Raw_Imigration data'!A:H, 8, FALSE) -> 162386 | D33: ='Raw_Gross Domestic Product '!AG3 -> 15599.7 | E33: =((D33-D32)/D32)*100 -> 3.6593794 | F33: ='Raw_Personal Income and Its Dis'!AH3 -> 13309.6 | G33: =Raw_Unemployment!B33 -> 107.2 | H33: =B32 -> 261671 | I33: =E32 -> 3.943197 | K33: =B33 -> 405965 | L33: =G33 -> 107.2 | M33: =H33 -> 261671 | Y33: =E33 -> 3.6593794 | Z33: =B33 -> 405965 | AA33: =H33 -> 261671 | AD33: =B33 -> 405965 | AE33: =D33 -> 15599.7 | AF33: =G33 -> 107.2
A34: 2012 | B34: =VLOOKUP(A34,'Raw_Imigration data'!A:G, 7, FALSE) -> 443126 | C34: =VLOOKUP(A34,'Raw_Imigration data'!A:H, 8, FALSE) -> 177250.4 | D34: ='Raw_Gross Domestic Product '!AH3 -> 16254 | E34: =((D34-D33)/D33)*100 -> 4.1943114 | F34: ='Raw_Personal Income and Its Dis'!AI3 -> 13917.8 | G34: =Raw_Unemployment!B34 -> 96.9 | H34: =B33 -> 405965 | I34: =E33 -> 3.6593794 | K34: =B34 -> 443126 | L34: =G34 -> 96.9 | M34: =H34 -> 405965 | O34: ANOVA | Y34: =E34 -> 4.1943114 | Z34: =B34 -> 443126 | AA34: =H34 -> 405965 | AD34: =B34 -> 443126 | AE34: =D34 -> 16254 | AF34: =G34 -> 96.9
A35: 2013 | B35: =VLOOKUP(A35,'Raw_Imigration data'!A:G, 7, FALSE) -> 449288 | C35: =VLOOKUP(A35,'Raw_Imigration data'!A:H, 8, FALSE) -> 179715.2 | D35: ='Raw_Gross Domestic Product '!AI3 -> 16880.7 | E35: =((D35-D34)/D34)*100 -> 3.8556663 | F35: ='Raw_Personal Income and Its Dis'!AJ3 -> 14068.8 | G35: =Raw_Unemployment!B35 -> 88.3 | H35: =B34 -> 443126 | I35: =E34 -> 4.1943114 | K35: =B35 -> 449288 | L35: =G35 -> 88.3 | M35: =H35 -> 443126 | P35: df | Q35: SS | R35: MS | S35: F | T35: Significance F | Y35: =E35 -> 3.8556663 | Z35: =B35 -> 449288 | AA35: =H35 -> 443126 | AD35: =B35 -> 449288 | AE35: =D35 -> 16880.7 | AF35: =G35 -> 88.3
A36: 2014 | B36: =VLOOKUP(A36,'Raw_Imigration data'!A:G, 7, FALSE) -> 517631 | C36: =VLOOKUP(A36,'Raw_Imigration data'!A:H, 8, FALSE) -> 207052.4 | D36: ='Raw_Gross Domestic Product '!AJ3 -> 17608.1 | E36: =((D36-D35)/D35)*100 -> 4.309063 | F36: ='Raw_Personal Income and Its Dis'!AK3 -> 14784.1 | G36: =Raw_Unemployment!B36 -> 73.9 | H36: =B35 -> 449288 | I36: =E35 -> 3.8556663 | K36: =B36 -> 517631 | L36: =G36 -> 73.9 | M36: =H36 -> 449288 | O36: Regression | P36: 3 | Q36: 3250.8956 | R36: 1083.6319 | S36: 3.5272752 | T36: 0.025412066 | Y36: =E36 -> 4.309063 | Z36: =B36 -> 517631 | AA36: =H36 -> 449288 | AD36: =B36 -> 517631 | AE36: =D36 -> 17608.1 | AF36: =G36 -> 73.9
A37: 2015 | B37: =VLOOKUP(A37,'Raw_Imigration data'!A:G, 7, FALSE) -> 667012 | C37: =VLOOKUP(A37,'Raw_Imigration data'!A:H, 8, FALSE) -> 266804.8 | D37: ='Raw_Gross Domestic Product '!AK3 -> 18295 | E37: =((D37-D36)/D36)*100 -> 3.9010455 | F37: ='Raw_Personal Income and Its Dis'!AL3 -> 15473.7 | G37: =Raw_Unemployment!B37 -> 63.3 | H37: =B36 -> 517631 | I37: =E36 -> 4.309063 | K37: =B37 -> 667012 | L37: =G37 -> 63.3 | M37: =H37 -> 517631 | O37: Residual | P37: 33 | Q37: 10138.095 | R37: 307.21501 | Y37: =E37 -> 3.9010455 | Z37: =B37 -> 667012 | AA37: =H37 -> 517631 | AD37: =B37 -> 667012 | AE37: =D37 -> 18295 | AF37: =G37 -> 63.3
A38: 2015 | B38: =VLOOKUP(A38,'Raw_Imigration data'!A:G, 7, FALSE) -> 667012 | C38: =VLOOKUP(A38,'Raw_Imigration data'!A:H, 8, FALSE) -> 266804.8 | D38: ='Raw_Gross Domestic Product '!AK4 -> 12297.4 | E38: =((D38-D37)/D37)*100 -> -32.782728 | F38: ='Raw_Personal Income and Its Dis'!AL4 -> 9699.4 | G38: =Raw_Unemployment!B38 -> 58.5 | H38: =B37 -> 667012 | I38: =E37 -> 3.9010455 | K38: =B38 -> 667012 | L38: =G38 -> 58.5 | M38: =H38 -> 667012 | O38: Total | P38: 36 | Q38: 13388.991 | Y38: =E38 -> -32.782728 | Z38: =B38 -> 667012 | AA38: =H38 -> 667012 | AD38: =B38 -> 667012 | AE38: =D38 -> 12297.4 | AF38: =G38 -> 58.5
P40: Coefficients | Q40: Standard Error | R40: t Stat | S40: P-value | T40: Lower 95% | U40: Upper 95% | V40: Lower 95.0% | W40: Upper 95.0%
O41: Intercept | P41: 76.157958 | Q41: 3.4390623 | R41: 22.144977 | S41: 2.2254976e-21 | T41: 69.161133 | U41: 83.154783 | V41: 69.161133 | W41: 83.154783
O42: GDP Growth Rate | P42: 0.76536121 | Q42: 0.46557894 | R42: 1.6438914 | S42: 0.10969376 | T42: -0.18186626 | U42: 1.7125887 | V42: -0.18186626 | W42: 1.7125887
O43: Net Immigration | P43: -3.6248466e-06 | Q43: 1.0657978e-05 | R43: -0.34010641 | S43: 0.73593184 | T43: -2.5308666e-05 | U43: 1.8058972e-05 | V43: -2.5308666e-05 | W43: 1.8058972e-05
O44: Immigration Lag1 | P44: 2.3668886e-05 | Q44: 1.1004417e-05 | R44: 2.1508533 | S44: 0.038905951 | T44: 1.2802323e-06 | U44: 4.605754e-05 | V44: 1.2802323e-06 | W44: 4.605754e-05
O50: SUMMARY OUTPUT | P50: Model 3
O52: Regression Statistics
O53: Multiple R | P53: 0.99937051
O54: R Square | P54: 0.99874142
O55: Adjusted R Square | P55: 0.99862701
O56: Standard Error | P56: 146.071
O57: Observations | P57: 37
O59: ANOVA
P60: df | Q60: SS | R60: MS | S60: F | T60: Significance F
O61: Regression | P61: 3 | Q61: 5.5874738e+08 | R61: 1.8624913e+08 | S61: 8729.0353 | T61: 6.5860689e-48
O62: Residual | P62: 33 | Q62: 704112.3 | R62: 21336.736
O63: Total | P63: 36 | Q63: 5.5945149e+08
P65: Coefficients | Q65: Standard Error | R65: t Stat | S65: P-value | T65: Lower 95% | U65: Upper 95% | V65: Lower 95.0% | W65: Upper 95.0%
O66: Intercept | P66: -427.58535 | Q66: 139.08116 | R66: -3.0743585 | S66: 0.004214462 | T66: -710.54811 | U66: -144.6226 | V66: -710.54811 | W66: -144.6226
O67: Net Immigration | P67: -5.4751729e-05 | Q67: 5.7559669e-05 | R67: -0.95121688 | S67: 0.34840962 | T67: -0.00017185776 | U67: 6.2354299e-05 | V67: -0.00017185776 | W67: 6.2354299e-05
O68: GDP Nominal | P68: 0.84797794 | Q68: 0.0059103986 | R68: 143.47221 | S68: 1.0242023e-47 | T68: 0.83595314 | U68: 0.86000273 | V68: 0.83595314 | W68: 0.86000273
O69: Unemployment Rate | P69: 3.2317381 | Q69: 1.3794085 | R69: 2.3428435 | S69: 0.025316355 | T69: 0.42531047 | U69: 6.0381658 | V69: 0.42531047 | W69: 6.0381658

Sheet Testing Data
A1: Year | B1: Net Immigration | C1: Immigration Rate | D1: GDP Nominal | E1: GDP Growth Rate | F1: Personal Income | G1: Unemployment Rate | H1: Immigration Lag1 | I1: GDP lag1 | M1: Model 1 | N1: Predicted GDP Growth | O1: Actual GDP Growth | P1: Error | Q1: Abs Error | R1: % Error
A2: 2016 | B2: ='Master Dataset'!B38 -> 829752 | C2: ='Master Dataset'!C38 -> 331900.8 | D2: ='Master Dataset'!D38 -> 18804.9 | E2: ='Master Dataset'!E38 -> 2.7871003 | F2: ='Master Dataset'!F38 -> 15887.7 | G2: ='Master Dataset'!G38 -> 58.5 | H2: ='Master Dataset'!H38 -> 667012 | I2: ='Master Dataset'!I38 -> 3.9010455 | M2: =A2 -> 2016 | N2: =('Training Data'!$P$18)+('Training Data'!$P$19*'Testing Data'!B2)+('Training Data'!$P$20*'Testing Data'!G2)+('Training Data'!$P$21*'Testing Data'!H2) -> -3.3979603 | O2: =E2 -> 2.7871003 | P2: =O2-N2 -> 6.1850606 | Q2: =ABS(P2) -> 6.1850606 | R2: =ABS((O2-N2)/O2) -> 2.219174
A3: 2017 | B3: ='Master Dataset'!B39 -> 796106 | C3: ='Master Dataset'!C39 -> 318442.4 | D3: ='Master Dataset'!D39 -> 19612.1 | E3: ='Master Dataset'!E39 -> 4.2924982 | F3: ='Master Dataset'!F39 -> 16662.8 | G3: ='Master Dataset'!G39 -> 52.3 | H3: ='Master Dataset'!H39 -> 829752 | I3: ='Master Dataset'!I39 -> 2.7871003 | M3: =A3 -> 2017 | N3: =('Training Data'!$P$18)+('Training Data'!$P$19*'Testing Data'!B3)+('Training Data'!$P$20*'Testing Data'!G3)+('Training Data'!$P$21*'Testing Data'!H3) -> -4.6776007 | O3: =E3 -> 4.2924982 | P3: =O3-N3 -> 8.9700989 | Q3: =ABS(P3) -> 8.9700989 | R3: =ABS((O3-N3)/O3) -> 2.0897152
A4: 2018 | B4: ='Master Dataset'!B40 -> 631502 | C4: ='Master Dataset'!C40 -> 252600.8 | D4: ='Master Dataset'!D40 -> 20656.5 | E4: ='Master Dataset'!E40 -> 5.3252839 | F4: ='Master Dataset'!F40 -> 17528.2 | G4: ='Master Dataset'!G40 -> 46.7 | H4: ='Master Dataset'!H40 -> 796106 | I4: ='Master Dataset'!I40 -> 4.2924982 | M4: =A4 -> 2018 | N4: =('Training Data'!$P$18)+('Training Data'!$P$19*'Testing Data'!B4)+('Training Data'!$P$20*'Testing Data'!G4)+('Training Data'!$P$21*'Testing Data'!H4) -> -4.6913786 | O4: =E4 -> 5.3252839 | P4: =O4-N4 -> 10.016662 | Q4: =ABS(P4) -> 10.016662 | R4: =ABS((O4-N4)/O4) -> 1.8809631
A5: 2019 | B5: ='Master Dataset'!B41 -> 543373 | C5: ='Master Dataset'!C41 -> 217349.2 | D5: ='Master Dataset'!D41 -> 21540 | E5: ='Master Dataset'!E41 -> 4.2771041 | F5: ='Master Dataset'!F41 -> 18363.2 | G5: ='Master Dataset'!G41 -> 44.1 | H5: ='Master Dataset'!H41 -> 631502 | I5: ='Master Dataset'!I41 -> 5.3252839 | M5: =A5 -> 2019 | N5: =('Training Data'!$P$18)+('Training Data'!$P$19*'Testing Data'!B5)+('Training Data'!$P$20*'Testing Data'!G5)+('Training Data'!$P$21*'Testing Data'!H5) -> -3.9995498 | O5: =E5 -> 4.2771041 | P5: =O5-N5 -> 8.2766539 | Q5: =ABS(P5) -> 8.2766539 | R5: =ABS((O5-N5)/O5) -> 1.935107
A6: 2020 | B6: ='Master Dataset'!B42 -> 313888 | C6: ='Master Dataset'!C42 -> 125555.2 | D6: ='Master Dataset'!D42 -> 21375.3 | E6: ='Master Dataset'!E42 -> -0.76462396 | F6: ='Master Dataset'!F42 -> 19631.7 | G6: ='Master Dataset'!G42 -> 97.2 | H6: ='Master Dataset'!H42 -> 543373 | I6: ='Master Dataset'!I42 -> 4.2771041 | M6: =A6 -> 2020 | N6: =('Training Data'!$P$18)+('Training Data'!$P$19*'Testing Data'!B6)+('Training Data'!$P$20*'Testing Data'!G6)+('Training Data'!$P$21*'Testing Data'!H6) -> 2.3676033 | O6: =E6 -> -0.76462396 | P6: =O6-N6 -> -3.1322273 | Q6: =ABS(P6) -> 3.1322273 | R6: =ABS((O6-N6)/O6) -> 4.0964284
A7: 2021 | B7: ='Master Dataset'!B43 -> 484038 | C7: ='Master Dataset'!C43 -> 193615.2 | D7: ='Master Dataset'!D43 -> 23725.6 | E7: ='Master Dataset'!E43 -> 10.995401 | F7: ='Master Dataset'!F43 -> 21498.9 | G7: ='Master Dataset'!G43 -> 64.3 | H7: ='Master Dataset'!H43 -> 313888 | I7: ='Master Dataset'!I43 -> -0.76462396 | M7: =A7 -> 2021 | N7: =('Training Data'!$P$18)+('Training Data'!$P$19*'Testing Data'!B7)+('Training Data'!$P$20*'Testing Data'!G7)+('Training Data'!$P$21*'Testing Data'!H7) -> -0.36976263 | O7: =E7 -> 10.995401 | P7: =O7-N7 -> 11.365164 | Q7: =ABS(P7) -> 11.365164 | R7: =ABS((O7-N7)/O7) -> 1.0336288
A9: Model 1
A10: MAE | B10: =AVERAGE(Q2:Q7) -> 7.9909778
A11: RMSE | B11: =SQRT(SUMPRODUCT((P2:P7)^2)/6) -> 8.4314093 | M11: Model 2 | N11: Predicted Unemployment | O11: Actual Unemployment | P11: Error | Q11: Abs Error | R11: % Error
A12: MAPE | B12: =AVERAGE(R2:R7) -> 2.2091694 | M12: =A2 -> 2016 | N12: =('Training Data'!$P$41)+('Training Data'!$P$42*'Testing Data'!B2)+('Training Data'!$P$20*'Testing Data'!G2)+('Training Data'!$P$21*'Testing Data'!H2) -> 635139.12 | O12: =G2 -> 58.5 | P12: =O12-N12 -> -635080.62 | Q12: =ABS(P12) -> 635080.62 | R12: =ABS((O12-N12)/O12) -> 10856.079
A13: Prediction Accuracy | B13: =100%-B12 -> -1.2091694 | M13: =A3 -> 2017 | N13: =('Training Data'!$P$41)+('Training Data'!$P$42*'Testing Data'!B3)+('Training Data'!$P$20*'Testing Data'!G3)+('Training Data'!$P$21*'Testing Data'!H3) -> 609386.41 | O13: =G3 -> 52.3 | P13: =O13-N13 -> -609334.11 | Q13: =ABS(P13) -> 609334.11 | R13: =ABS((O13-N13)/O13) -> 11650.748
M14: =A4 -> 2018 | N14: =('Training Data'!$P$41)+('Training Data'!$P$42*'Testing Data'!B4)+('Training Data'!$P$20*'Testing Data'!G4)+('Training Data'!$P$21*'Testing Data'!H4) -> 483404.47 | O14: =G4 -> 46.7 | P14: =O14-N14 -> -483357.77 | Q14: =ABS(P14) -> 483357.77 | R14: =ABS((O14-N14)/O14) -> 10350.274
M15: =A5 -> 2019 | N15: =('Training Data'!$P$41)+('Training Data'!$P$42*'Testing Data'!B5)+('Training Data'!$P$20*'Testing Data'!G5)+('Training Data'!$P$21*'Testing Data'!H5) -> 415954.43 | O15: =G5 -> 44.1 | P15: =O15-N15 -> -415910.33 | Q15: =ABS(P15) -> 415910.33 | R15: =ABS((O15-N15)/O15) -> 9431.0732
A16: Model 2 | M16: =A6 -> 2020 | N16: =('Training Data'!$P$41)+('Training Data'!$P$42*'Testing Data'!B6)+('Training Data'!$P$20*'Testing Data'!G6)+('Training Data'!$P$21*'Testing Data'!H6) -> 240321.31 | O16: =G6 -> 97.2 | P16: =O16-N16 -> -240224.11 | Q16: =ABS(P16) -> 240224.11 | R16: =ABS((O16-N16)/O16) -> 2471.4415
A17: MAE | B17: =AVERAGE(Q12:Q17) -> 459064.64 | M17: =A7 -> 2021 | N17: =('Training Data'!$P$41)+('Training Data'!$P$42*'Testing Data'!B7)+('Training Data'!$P$20*'Testing Data'!G7)+('Training Data'!$P$21*'Testing Data'!H7) -> 370545.21 | O17: =G7 -> 64.3 | P17: =O17-N17 -> -370480.91 | Q17: =ABS(P17) -> 370480.91 | R17: =ABS((O17-N17)/O17) -> 5761.7559
A18: RMSE | B18: =SQRT(SUMPRODUCT((P12:P17)^2)/6) -> 478921.59
A19: MAPE | B19: =AVERAGE(R12:R17) -> 8420.2285
A20: Prediction Accuracy | B20: =100%-B19 -> -8419.2285
M21: Model 3 | N21: Predicted Income Growth | O21: Actual Income Growth | P21: Error | Q21: Abs Error | R21: %Error
A22: Model 3 | M22: =A2 -> 2016 | N22: =('Training Data'!$P$66)+('Training Data'!$P$67*'Testing Data'!B2)+('Training Data'!$P$68*'Testing Data'!D2)+('Training Data'!$P$69*'Testing Data'!G2) -> 15662.181 | O22: =D2 -> 18804.9 | P22: =O22-N22 -> 3142.7188 | Q22: =ABS(P22) -> 3142.7188 | R22: =ABS((O22-N22)/O22) -> 0.16712233
A23: MAE | B23: =AVERAGE(Q22:Q27) -> 3450.0772 | M23: =A3 -> 2017 | N23: =('Training Data'!$P$66)+('Training Data'!$P$67*'Testing Data'!B3)+('Training Data'!$P$68*'Testing Data'!D3)+('Training Data'!$P$69*'Testing Data'!G3) -> 16328.474 | O23: =D3 -> 19612.1 | P23: =O23-N23 -> 3283.6256 | Q23: =ABS(P23) -> 3283.6256 | R23: =ABS((O23-N23)/O23) -> 0.16742855
A24: RMSE | B24: =SQRT(SUMPRODUCT((P22:P27)^2)/6) -> 3457.5303 | M24: =A4 -> 2018 | N24: =('Training Data'!$P$66)+('Training Data'!$P$67*'Testing Data'!B4)+('Training Data'!$P$68*'Testing Data'!D4)+('Training Data'!$P$69*'Testing Data'!G4) -> 17205.017 | O24: =D4 -> 20656.5 | P24: =O24-N24 -> 3451.4828 | Q24: =ABS(P24) -> 3451.4828 | R24: =ABS((O24-N24)/O24) -> 0.16708943
A25: MAPE | B25: =AVERAGE(R22:R27) -> 0.16480243 | M25: =A5 -> 2019 | N25: =('Training Data'!$P$66)+('Training Data'!$P$67*'Testing Data'!B5)+('Training Data'!$P$68*'Testing Data'!D5)+('Training Data'!$P$69*'Testing Data'!G5) -> 17950.628 | O25: =D5 -> 21540 | P25: =O25-N25 -> 3589.3716 | Q25: =ABS(P25) -> 3589.3716 | R25: =ABS((O25-N25)/O25) -> 0.16663749
A26: Prediction Accuracy | B26: =100%-B25 -> 0.83519757 | M26: =A6 -> 2020 | N26: =('Training Data'!$P$66)+('Training Data'!$P$67*'Testing Data'!B6)+('Training Data'!$P$68*'Testing Data'!D6)+('Training Data'!$P$69*'Testing Data'!G6) -> 17995.136 | O26: =D6 -> 21375.3 | P26: =O26-N26 -> 3380.1636 | Q26: =ABS(P26) -> 3380.1636 | R26: =ABS((O26-N26)/O26) -> 0.15813409
M27: =A7 -> 2021 | N27: =('Training Data'!$P$66)+('Training Data'!$P$67*'Testing Data'!B7)+('Training Data'!$P$68*'Testing Data'!D7)+('Training Data'!$P$69*'Testing Data'!G7) -> 19872.499 | O27: =D7 -> 23725.6 | P27: =O27-N27 -> 3853.1012 | Q27: =ABS(P27) -> 3853.1012 | R27: =ABS((O27-N27)/O27) -> 0.16240269

Sheet Visualization
A1: Model | B1: Immigration coefficient | J1: Model | K1: Training R2 | R1: P-value Heatmap | AJ1: Year | AK1: Net Immigration | AL1: ='Master Dataset'!E1 -> GDP Growth Rate | AM1: Unemployment Rate | AN1: ='Master Dataset'!F1 -> Personal Income
A2: Model 1 | B2: ='Training Data'!P19 -> -2.4616384e-06 | J2: Model 1 | K2: 0.20846616 | AJ2: 1980 | AK2: ='Master Dataset'!B2 -> -5813 | AM2: ='Master Dataset'!G2 -> 86.1 | AN2: ='Master Dataset'!F2 -> 2324.5
A3: Model 2 | B3: ='Training Data'!P43 -> -3.6248466e-06 | J3: Model 2 | K3: 0.24280363 | R3: Variables | S3: Model 1 | T3: Model 2 | U3: Model 3 | AJ3: 1981 | AK3: ='Master Dataset'!B3 -> -86988 | AL3: ='Master Dataset'!E3 -> 12.238827 | AM3: ='Master Dataset'!G3 -> 91.4 | AN3: ='Master Dataset'!F3 -> 2603.2
A4: Model 3 | B4: ='Training Data'!P67 -> -5.4751729e-05 | J4: Model 3 | K4: 0.99874142 | R4: Net Immigration | S4: ='Training Data'!S19 -> 0.52651081 | T4: ='Training Data'!S43 -> 0.73593184 | U4: ='Training Data'!S67 -> 0.34840962 | AJ4: 1982 | AK4: ='Master Dataset'!B4 -> -196068 | AL4: ='Master Dataset'!E4 -> 4.2656688 | AM4: ='Master Dataset'!G4 -> 116.5 | AN4: ='Master Dataset'!F4 -> 2789.5
R5: GPD Growth | T5: ='Training Data'!S42 -> 0.10969376 | U5: ='Training Data'!S68 -> 1.0242023e-47 | AJ5: 1983 | AK5: ='Master Dataset'!B5 -> -339541 | AL5: ='Master Dataset'!E5 -> 8.6787487 | AM5: ='Master Dataset'!G5 -> 115.2 | AN5: ='Master Dataset'!F5 -> 2981.7
R6: Unemployment | S6: ='Training Data'!S20 -> 0.10370822 | U6: ='Training Data'!S69 -> 0.025316355 | AJ6: 1984 | AK6: ='Master Dataset'!B6 -> -316325 | AL6: ='Master Dataset'!E6 -> 11.106219 | AM6: ='Master Dataset'!G6 -> 90.1 | AN6: ='Master Dataset'!F6 -> 3288.7
AJ7: 1985 | AK7: ='Master Dataset'!B7 -> -428548 | AL7: ='Master Dataset'!E7 -> 7.4648306 | AM7: ='Master Dataset'!G7 -> 86.3 | AN7: ='Master Dataset'!F7 -> 3522.9
AJ8: 1986 | AK8: ='Master Dataset'!B8 -> -948739 | AL8: ='Master Dataset'!E8 -> 5.5450565 | AM8: ='Master Dataset'!G8 -> 84 | AN8: ='Master Dataset'!F8 -> 3731.2
AJ9: 1987 | AK9: ='Master Dataset'!B9 -> -451122 | AL9: ='Master Dataset'!E9 -> 6.0179928 | AM9: ='Master Dataset'!G9 -> 74.1 | AN9: ='Master Dataset'!F9 -> 3946.8
AJ10: 1988 | AK10: ='Master Dataset'!B10 -> -219790 | AL10: ='Master Dataset'!E10 -> 7.8513758 | AM10: ='Master Dataset'!G10 -> 65.9 | AN10: ='Master Dataset'!F10 -> 4280
AJ11: 1989 | AK11: ='Master Dataset'!B11 -> 331925 | AL11: ='Master Dataset'!E11 -> 7.7381407 | AM11: ='Master Dataset'!G11 -> 63.1 | AN11: ='Master Dataset'!F11 -> 4621
AJ12: 1990 | AK12: ='Master Dataset'!B12 -> 605366 | AL12: ='Master Dataset'!E12 -> 5.6987379 | AM12: ='Master Dataset'!G12 -> 67.4 | AN12: ='Master Dataset'!F12 -> 4913.3
AJ13: 1991 | AK13: ='Master Dataset'!B13 -> 845690 | AL13: ='Master Dataset'!E13 -> 3.2701112 | AM13: ='Master Dataset'!G13 -> 82.2 | AN13: ='Master Dataset'!F13 -> 5089.9
AJ14: 1992 | AK14: ='Master Dataset'!B14 -> -60507 | AL14: ='Master Dataset'!E14 -> 5.8816843 | AM14: ='Master Dataset'!G14 -> 89.9 | AN14: ='Master Dataset'!F14 -> 5417.5
AJ15: 1993 | AK15: ='Master Dataset'!B15 -> -267855 | AL15: ='Master Dataset'!E15 -> 5.1884116 | AM15: ='Master Dataset'!G15 -> 82.9 | AN15: ='Master Dataset'!F15 -> 5652.9
AJ16: 1994 | AK16: ='Master Dataset'!B16 -> -159108 | AL16: ='Master Dataset'!E16 -> 6.2490887 | AM16: ='Master Dataset'!G16 -> 73.2 | AN16: ='Master Dataset'!F16 -> 5940.9
AJ17: 1995 | AK17: ='Master Dataset'!B17 -> -545538 | AL17: ='Master Dataset'!E17 -> 4.8372489 | AM17: ='Master Dataset'!G17 -> 67.1 | AN17: ='Master Dataset'!F17 -> 6283.4
AJ18: 1996 | AK18: ='Master Dataset'!B18 -> -652127 | AL18: ='Master Dataset'!E18 -> 5.6729976 | AM18: ='Master Dataset'!G18 -> 64.9 | AN18: ='Master Dataset'!F18 -> 6666.2
... AJ43: 2021 | AK43: ='Master Dataset'!B43 -> 484038 | AL43: ='Master Dataset'!E43 -> 10.995401 | AM43: ='Master Dataset'!G43 -> 64.3 | AN43: ='Master Dataset'!F43 -> 21498.9

Sheet Raw_Imigration data
A1: Year | B1: Immigrants Obtaining Lawful Permanent Resident Status | C1: Refugee Arrivals | D1: Noncitizen Apprehensions | E1: Noncitizen Removals | F1: Noncitizen Returns | G1: Net Immigration | H1: Immigration rate per 100K | I1: Net Immigration 3yr Avg
A2: 1980 | B2: 524295 | C2: 207116 | D2: 910361 | E2: 18013 | F2: 719211 | G2: =B2+C2-E2-F2 -> -5813 | H2: =(G2/250000)*100000 -> -2325.2
A3: 1981 | B3: 595014 | C3: 159252 | D3: 975780 | E3: 17379 | F3: 823875 | G3: =B3+C3-E3-F3 -> -86988 | H3: =(G3/250000)*100000 -> -34795.2
A4: 1982 | B4: 533624 | C4: 98096 | D4: 970246 | E4: 15216 | F4: 812572 | G4: =B4+C4-E4-F4 -> -196068 | H4: =(G4/250000)*100000 -> -78427.2 | I4: =AVERAGE(G2:G4) -> -96289.667
A5: 1983 | B5: 550052 | C5: 61218 | D5: 1251357 | E5: 19211 | F5: 931600 | G5: =B5+C5-E5-F5 -> -339541 | H5: =(G5/250000)*100000 -> -135816.4 | I5: =AVERAGE(G3:G5) -> -207532.33
A6: 1984 | B6: 541811 | C6: 70393 | D6: 1246981 | E6: 18696 | F6: 909833 | G6: =B6+C6-E6-F6 -> -316325 | H6: =(G6/250000)*100000 -> -126530 | I6: =AVERAGE(G4:G6) -> -283978
A7: 1985 | B7: 568149 | C7: 67704 | D7: 1348749 | E7: 23105 | F7: 1041296 | G7: =B7+C7-E7-F7 -> -428548 | H7: =(G7/250000)*100000 -> -171419.2 | I7: =AVERAGE(G5:G7) -> -361471.33
A8: 1986 | B8: 600027 | C8: 62146 | D8: 1767400 | E8: 24592 | F8: 1586320 | G8: =B8+C8-E8-F8 -> -948739 | H8: =(G8/250000)*100000 -> -379495.6 | I8: =AVERAGE(G6:G8) -> -564537.33
A9: 1987 | B9: 599889 | C9: 64528 | D9: 1190488 | E9: 24336 | F9: 1091203 | G9: =B9+C9-E9-F9 -> -451122 | H9: =(G9/250000)*100000 -> -180448.8 | I9: =AVERAGE(G7:G9) -> -609469.67
A10: 1988 | B10: 641346 | C10: 76483 | D10: 1008145 | E10: 25829 | F10: 911790 | G10: =B10+C10-E10-F10 -> -219790 | H10: =(G10/250000)*100000 -> -87916 | I10: =AVERAGE(G8:G10) -> -539883.67
A11: 1989 | B11: 1090172 | C11: 107070 | D11: 954243 | E11: 34427 | F11: 830890 | G11: =B11+C11-E11-F11 -> 331925 | H11: =(G11/250000)*100000 -> 132770 | I11: =AVERAGE(G9:G11) -> -112995.67
A12: 1990 | B12: 1535872 | C12: 122066 | D12: 1169939 | E12: 30039 | F12: 1022533 | G12: =B12+C12-E12-F12 -> 605366 | H12: =(G12/250000)*100000 -> 242146.4 | I12: =AVERAGE(G10:G12) -> 239167
A13: 1991 | B13: 1826595 | C13: 113389 | D13: 1197875 | E13: 33189 | F13: 1061105 | G13: =B13+C13-E13-F13 -> 845690 | H13: =(G13/250000)*100000 -> 338276 | I13: =AVERAGE(G11:G13) -> 594327
A14: 1992 | B14: 973445 | C14: 115548 | D14: 1258481 | E14: 43671 | F14: 1105829 | G14: =B14+C14-E14-F14 -> -60507 | H14: =(G14/250000)*100000 -> -24202.8 | I14: =AVERAGE(G12:G14) -> 463516.33
A15: 1993 | B15: 903916 | C15: 114181 | D15: 1327261 | E15: 42542 | F15: 1243410 | G15: =B15+C15-E15-F15 -> -267855 | H15: =(G15/250000)*100000 -> -107142 | I15: =AVERAGE(G13:G15) -> 172442.67
... A43: 2021 | B43: 740002 | C43: 11454 | D43: 1865379 | E43: 89191 | F43: 178227 | G43: =B43+C43-E43-F43 -> 484038 | H43: =(G43/250000)*100000 -> 193615.2 | I43: =AVERAGE(G41:G43) -> 447099.67

Sheet Raw_Gross Domestic Product 
B1: 1980 | C1: 1981 | D1: 1982 | E1: 1983 | F1: 1984 | G1: 1985 | H1: 1986 | I1: 1987 | J1: 1988 | K1: 1989 | L1: 1990 | M1: 1991 | N1: 1992 | O1: 1993 | P1: 1994 | Q1: 1995 | R1: 1996 | S1: 1997 | T1: 1998 | U1: 1999 | V1: 2000 | W1: 2001 | X1: 2002 | Y1: 2003 | Z1: 2004 | AA1: 2005 | AB1: 2006 | AC1: 2007 | AD1: 2008 | AE1: 2009 | AF1: 2010 | AG1: 2011 | AH1: 2012 | AI1: 2013 | AJ1: 2014 | AK1: 2015 | AL1: 2016 | AM1: 2017 | AN1: 2018 | AO1: 2019 | AP1: 2020 | AQ1: 2021
A3: Gross domestic product | B3: 2857.3 | C3: 3207 | D3: 3343.8 | E3: 3634 | F3: 4037.6 | G3: 4339 | H3: 4579.6 | I3: 4855.2 | J3: 5236.4 | K3: 5641.6 | L3: 5963.1 | M3: 6158.1 | N3: 6520.3 | O3: 6858.6 | P3: 7287.2 | Q3: 7639.7 | R3: 8073.1 | S3: 8577.6 | T3: 9062.8 | U3: 9631.2 | V3: 10251 | W3: 10581.9 | X3: 10929.1 | Y3: 11456.5 | Z3: 12217.2 | AA3: 13039.2 | AB3: 13815.6 | AC3: 14474.2 | AD3: 14769.9 | AE3: 14478.1 | AF3: 15049 | AG3: 15599.7 | AH3: 16254 | AI3: 16880.7 | AJ3: 17608.1 | AK3: 18295 | AL3: 18804.9 | AM3: 19612.1 | AN3: 20656.5 | AO3: 21540 | AP3: 21375.3 | AQ3: 23725.6
A4: Personal consumption expenditures | B4: 1750.7 | C4: 1934 | D4: 2071.3 | E4: 2281.6 | F4: 2492.3 | G4: 2712.8 | H4: 2886.3 | I4: 3076.3 | J4: 3330 | K4: 3576.8 | L4: 3809 | M4: 3943.4 | N4: 4197.6 | O4: 4452 | P4: 4721 | Q4: 4962.6 | R4: 5244.6 | S4: 5536.8 | T4: 5877.2 | U4: 6283.8 | V4: 6767.2 | W4: 7073.8 | X4: 7348.9 | Y4: 7740.7 | Z4: 8232 | AA4: 8769.1 | AB4: 9277.2 | AC4: 9746.6 | AD4: 10050.1 | AE4: 9891.2 | AF4: 10260.3 | AG4: 10698.9 | AH4: 11047.4 | AI4: 11388.2 | AJ4: 11874.5 | AK4: 12297.4 | AL4: 12726.8 | AM4: 13290.6 | AN4: 13934.4 | AO4: 14437.5 | AP4: 14231.4 | AQ4: 16119.7
A5: Goods | B5: 799.8 | C5: 869.4 | D5: 899.3 | E5: 973.8 | F5: 1063.7 | G5: 1137.6 | H5: 1195.6 | I5: 1256.3 | J5: 1337.3 | K5: 1423.8 | L5: 1491.3 | M5: 1497.4 | N5: 1563.3 | O5: 1642.3 | P5: 1746.6 | Q5: 1815.5 | R5: 1917.7 | S5: 2006.5 | T5: 2108.4 | U5: 2287.1 | V5: 2453.2 | W5: 2525.6 | X5: 2598.8 | Y5: 2722.6 | Z5: 2902 | AA5: 3082.9 | AB5: 3239.7 | AC5: 3367 | AD5: 3363.2 | AE5: 3180 | AF5: 3317.8 | AG5: 3518.1 | AH5: 3637.7 | AI5: 3742.2 | AJ5: 3886.6 | AK5: 3955.1 | AL5: 4033 | AM5: 4212.2 | AN5: 4414.2 | AO5: 4532.8 | AP5: 4708.6 | AQ5: 5499.4
A6: Durable goods | B6: 226.4 | C6: 243.9 | D6: 253 | E6: 295 | F6: 342.2 | G6: 380.4 | H6: 421.4 | I6: 442 | J6: 475.1 | K6: 494.3 | L6: 497.1 | M6: 477.2 | N6: 508.1 | O6: 551.5 | P6: 607.2 | Q6: 635.7 | R6: 676.3 | S6: 715.5 | T6: 779.3 | U6: 855.6 | V6: 912.6 | W6: 941.5 | X6: 985.4 | Y6: 1017.8 | Z6: 1080.6 | AA6: 1128.6 | AB6: 1158.3 | AC6: 1188 | AD6: 1098.8 | AE6: 1012.1 | AF6: 1049 | AG6: 1093.5 | AH6: 1144.2 | AI6: 1191.8 | AJ6: 1247.3 | AK6: 1315.8 | AL6: 1356.5 | AM6: 1415.9 | AN6: 1488.8 | AO6: 1523.6 | AP6: 1621.7 | AQ6: 1991.9
A7: Nondurable goods | B7: 573.4 | C7: 625.4 | D7: 646.3 | E7: 678.8 | F7: 721.5 | G7: 757.2 | H7: 774.2 | I7: 814.3 | J7: 862.3 | K7: 929.5 | L7: 994.2 | M7: 1020.3 | N7: 1055.2 | O7: 1090.8 | P7: 1139.4 | Q7: 1179.8 | R7: 1241.4 | S7: 1291 | T7: 1329.1 | U7: 1431.5 | V7: 1540.6 | W7: 1584.1 | X7: 1613.4 | Y7: 1704.8 | Z7: 1821.4 | AA7: 1954.3 | AB7: 2081.3 | AC7: 2179 | AD7: 2264.5 | AE7: 2167.9 | AF7: 2268.9 | AG7: 2424.6 | AH7: 2493.5 | AI7: 2550.4 | AJ7: 2639.3 | AK7: 2639.3 | AL7: 2676.5 | AM7: 2796.3 | AN7: 2925.4 | AO7: 3009.2 | AP7: 3086.9 | AQ7: 3507.6
A8: Services | B8: 950.9 | C8: 1064.6 | D8: 1172 | E8: 1307.8 | F8: 1428.6 | G8: 1575.2 | H8: 1690.7 | I8: 1820 | J8: 1992.7 | K8: 2153 | L8: 2317.7 | M8: 2446 | N8: 2634.3 | O8: 2809.6 | P8: 2974.4 | Q8: 3147.1 | R8: 3326.9 | S8: 3530.3 | T8: 3768.8 | U8: 3996.7 | V8: 4314 | W8: 4548.2 | X8: 4750.1 | Y8: 5018.2 | Z8: 5329.9 | AA8: 5686.1 | AB8: 6037.6 | AC8: 6379.6 | AD8: 6686.9 | AE8: 6711.2 | AF8: 6942.4 | AG8: 7180.7 | AH8: 7409.6 | AI8: 7646.1 | AJ8: 7987.9 | AK8: 8342.3 | AL8: 8693.8 | AM8: 9078.4 | AN8: 9520.2 | AO8: 9904.7 | AP8: 9522.7 | AQ8: 10620.2
A9: Gross private domestic investment | B9: 530.1 | C9: 631.2 | D9: 581 | E9: 637.5 | F9: 820.1 | G9: 829.7 | H9: 849.1 | I9: 892.2 | J9: 937 | K9: 999.7 | L9: 993.4 | M9: 944.3 | N9: 1013 | O9: 1106.8 | P9: 1256.5 | Q9: 1317.5 | R9: 1432.1 | S9: 1595.6 | T9: 1736.7 | U9: 1887.1 | V9: 2038.4 | W9: 1934.8 | X9: 1930.4 | Y9: 2027.1 | Z9: 2281.3 | AA9: 2534.7 | AB9: 2701 | AC9: 2673 | AD9: 2477.6 | AE9: 1929.7 | AF9: 2165.5 | AG9: 2332.6 | AH9: 2621.8 | AI9: 2838.3 | AJ9: 3074 | AK9: 3288.5 | AL9: 3278.3 | AM9: 3467.7 | AN9: 3724.8 | AO9: 3893.7 | AP9: 3763.4 | AQ9: 4246.5
A10: Fixed investment | B10: 536.4 | C10: 601.4 | D10: 595.9 | E10: 643.3 | F10: 754.7 | G10: 807.8 | H10: 842.6 | I10: 865 | J10: 918.5 | K10: 972 | L10: 978.9 | M10: 944.7 | N10: 996.7 | O10: 1086 | P10: 1192.7 | Q10: 1286.3 | R10: 1401.3 | S10: 1524.7 | T10: 1673 | U10: 1826.2 | V10: 1983.9 | W10: 1973.1 | X10: 1910.4 | Y10: 2013 | Z10: 2217.2 | AA10: 2477.2 | AB10: 2632 | AC10: 2639.1 | AD10: 2506.9 | AE10: 2080.4 | AF10: 2111.6 | AG10: 2286.3 | AH10: 2550.5 | AI10: 2732.9 | AJ10: 2989.2 | AK10: 3148.4 | AL10: 3239.2 | AM10: 3435 | AN10: 3668.4 | AO10: 3820.8 | AP10: 3793.9 | AQ10: 4219.7
A11: Nonresidential | B11: 406.9 | C11: 472.9 | D11: 485.1 | E11: 482.2 | F11: 564.3 | G11: 607.8 | H11: 607.8 | I11: 615.2 | J11: 662.3 | K11: 716 | L11: 739.2 | M11: 723.6 | N11: 741.9 | O11: 799.2 | P11: 868.9 | Q11: 962.2 | R11: 1043.2 | S11: 1149.1 | T11: 1254.1 | U11: 1364.5 | V11: 1498.4 | W11: 1460.1 | X11: 1352.8 | Y11: 1375.9 | Z11: 1467.4 | AA11: 1621 | AB11: 1793.8 | AC11: 1948.6 | AD11: 1990.9 | AE11: 1690.4 | AF11: 1735 | AG11: 1907.5 | AH11: 2118.5 | AI11: 2221.3 | AJ11: 2425.2 | AK11: 2507.5 | AL11: 2529 | AM11: 2661.1 | AN11: 2856.5 | AO11: 2993.7 | AP11: 2873.3 | AQ11: 3087.2
A12: Structures | B12: 136.2 | C12: 167.3 | D12: 177.6 | E12: 154.3 | F12: 177.4 | G12: 194.5 | H12: 176.5 | I12: 174.2 | J12: 182.8 | K12: 193.7 | L12: 202.9 | M12: 183.6 | N12: 172.6 | O12: 177.2 | P12: 186.8 | Q12: 207.3 | R12: 224.6 | S12: 250.3 | T12: 276 | U12: 285.7 | V12: 321 | W12: 333.5 | X12: 287 | Y12: 286.6 | Z12: 307.7 | AA12: 353 | AB12: 425.2 | AC12: 510.3 | AD12: 571.1 | AE12: 455.8 | AF12: 379.8 | AG12: 404.5 | AH12: 479.4 | AI12: 491.5 | AJ12: 574.6 | AK12: 584.5 | AL12: 566.2 | AM12: 594.9 | AN12: 636.6 | AO12: 677.9 | AP12: 624.6 | AQ12: 627.9
A13: Equipment | B13: 216.4 | C13: 240.9 | D13: 234.9 | E13: 246.5 | F13: 291.9 | G13: 307.9 | H13: 317.7 | I13: 320.9 | J13: 346.8 | K13: 372.2 | L13: 371.9 | M13: 360.8 | N13: 381.7 | O13: 425.1 | P13: 476.4 | Q13: 528.1 | R13: 565.3 | S13: 610.9 | T13: 660 | U13: 713.6 | V13: 766.1 | W13: 711.5 | X13: 659.6 | Y13: 670.6 | Z13: 721.9 | AA13: 794.9 | AB13: 862.3 | AC13: 893.4 | AD13: 845.4 | AE13: 670.3 | AF13: 777 | AG13: 881.3 | AH13: 983.4 | AI13: 1035.3 | AJ13: 1109.1 | AK13: 1144.1 | AL13: 1119.8 | AM13: 1160 | AN13: 1227.6 | AO13: 1240.9 | AP13: 1112.5 | AQ13: 1196.3
A14: Intellectual property products | B14: 54.4 | C14: 64.8 | D14: 72.7 | E14: 81.3 | F14: 95 | G14: 105.3 | H14: 113.5 | I14: 120.1 | J14: 132.7 | K14: 150.1 | L14: 164.4 | M14: 179.1 | N14: 187.7 | O14: 196.9 | P14: 205.7 | Q14: 226.8 | R14: 253.3 | S14: 288 | T14: 318.1 | U14: 365.1 | V14: 411.3 | W14: 415 | X14: 406.2 | Y14: 418.7 | Z14: 437.8 | AA14: 473.1 | AB14: 506.3 | AC14: 544.8 | AD14: 574.4 | AE14: 564.4 | AF14: 578.2 | AG14: 621.7 | AH14: 655.7 | AI14: 694.6 | AJ14: 741.5 | AK14: 778.9 | AL14: 843 | AM14: 906.2 | AN14: 992.2 | AO14: 1074.9 | AP14: 1136.2 | AQ14: 1263.1
... A28: State and local | B28: 314.7 | C28: 340.4 | D28: 363.1 | E28: 384.2 | F28: 416.1 | G28: 457.6 | H28: 494.4 | I28: 528.7 | J28: 567.4 | K28: 617.8 | L28: 676.2 | M28: 716 | N28: 756 | O28: 784.8 | P28: 827.6 | Q28: 872.7 | R28: 913.7 | S28: 963.8 | T28: 1026.1 | U28: 1109.2 | V28: 1193.4 | W28: 1279.8 | X28: 1346.4 | Y28: 1383.8 | Z28: 1446 | AA28: 1527.5 | AB28: 1622.7 | AC28: 1739.5 | AD28: 1831.1 | AE28: 1855.6 | AF28: 1855.4 | AG28: 1848.2 | AH28: 1849.5 | AI28: 1905.2 | AJ28: 1951.5 | AK28: 2010.6 | AL28: 2065.7 | AM28: 2131.1 | AN28: 2244.1 | AO28: 2366.5 | AP28: 2474.5 | AQ28: 2604.3

Sheet Raw_Personal Income and Its Dis
A1: Line | C1: 1980 | D1: 1981 | E1: 1982 | F1: 1983 | G1: 1984 | H1: 1985 | I1: 1986 | J1: 1987 | K1: 1988 | L1: 1989 | M1: 1990 | N1: 1991 | O1: 1992 | P1: 1993 | Q1: 1994 | R1: 1995 | S1: 1996 | T1: 1997 | U1: 1998 | V1: 1999 | W1: 2000 | X1: 2001 | Y1: 2002 | Z1: 2003 | AA1: 2004 | AB1: 2005 | AC1: 2006 | AD1: 2007 | AE1: 2008 | AF1: 2009 | AG1: 2010 | AH1: 2011 | AI1: 2012 | AJ1: 2013 | AK1: 2014 | AL1: 2015 | AM1: 2016 | AN1: 2017 | AO1: 2018 | AP1: 2019 | AQ1: 2020 | AR1: 2021
A2: Line
A3: 1 | B3: Personal income | C3: 2324.5 | D3: 2603.2 | E3: 2789.5 | F3: 2981.7 | G3: 3288.7 | H3: 3522.9 | I3: 3731.2 | J3: 3946.8 | K3: 4280 | L3: 4621 | M3: 4913.3 | N3: 5089.9 | O3: 5417.5 | P3: 5652.9 | Q3: 5940.9 | R3: 6283.4 | S3: 6666.2 | T3: 7074 | U3: 7588.4 | V3: 7978.6 | W3: 8621.3 | X3: 8993.1 | Y3: 9150 | Z3: 9481.8 | AA3: 10015.9 | AB3: 10546.1 | AC3: 11302 | AD3: 11932.1 | AE3: 12425.7 | AF3: 12065.7 | AG3: 12556.6 | AH3: 13309.6 | AI3: 13917.8 | AJ3: 14068.8 | AK3: 14784.1 | AL3: 15473.7 | AM3: 15887.7 | AN3: 16662.8 | AO3: 17528.2 | AP3: 18363.2 | AQ3: 19631.7 | AR3: 21498.9
A4: 2 | B4: Compensation of employees | C4: 1622.2 | D4: 1792.5 | E4: 1893 | F4: 2012.5 | G4: 2215.9 | H4: 2387.3 | I4: 2542.1 | J4: 2722.4 | K4: 2948 | L4: 3139.6 | M4: 3340.4 | N4: 3450.5 | O4: 3668.2 | P4: 3817.3 | Q4: 4006.2 | R4: 4198.1 | S4: 4416.9 | T4: 4708.8 | U4: 5071.1 | V4: 5402.7 | W4: 5847.1 | X4: 6038.3 | Y4: 6135.1 | Z4: 6353.6 | AA4: 6719.5 | AB4: 7066.1 | AC4: 7479.7 | AD4: 7878.5 | AE4: 8056.8 | AF4: 7759 | AG4: 7925.4 | AH4: 8226.2 | AI4: 8567.4 | AJ4: 8835 | AK4: 9250.2 | AL4: 9699.4 | AM4: 9966.1 | AN4: 10424.4 | AO4: 10957.4 | AP4: 11446.6 | AQ4: 11598.1 | AR4: 12558.4
A5: 3 | B5: Wages and salaries | C5: 1373.4 | D5: 1511.4 | E5: 1587.5 | F5: 1677.5 | G5: 1844.9 | H5: 1982.6 | I5: 2102.3 | J5: 2256.3 | K5: 2439.8 | L5: 2583.1 | M5: 2741.2 | N5: 2814.5 | O5: 2965.5 | P5: 3079.3 | Q5: 3236.6 | R5: 3418 | S5: 3616.5 | T5: 3876.8 | U5: 4181.6 | V5: 4457.9 | W5: 4824.9 | X5: 4953.6 | Y5: 4995.8 | Z5: 5138.3 | AA5: 5421 | AB5: 5691.4 | AC5: 6056.7 | AD5: 6396.4 | AE5: 6534.1 | AF5: 6249.1 | AG5: 6372.5 | AH5: 6626.2 | AI5: 6928.1 | AJ5: 7114 | AK5: 7476.3 | AL5: 7859.5 | AM5: 8091.2 | AN5: 8474.4 | AO5: 8899.8 | AP5: 9325.1 | AQ5: 9465.3 | AR5: 10315
A6: 4 | B6: Private industries | C6: 1112 | D6: 1225.5 | E6: 1280 | F6: 1352.7 | G6: 1496.8 | H6: 1608.7 | I6: 1705.1 | J6: 1833.2 | K6: 1987.7 | L6: 2101.9 | M6: 2222.2 | N6: 2265.7 | O6: 2393.5 | P6: 2490.3 | Q6: 2627.1 | R6: 2789 | S6: 2968.4 | T6: 3205 | U6: 3480.3 | V6: 3724.2 | W6: 4045.2 | X6: 4131.6 | Y6: 4123 | Z6: 4224.3 | AA6: 4468.7 | AB6: 4700.1 | AC6: 5022.2 | AD6: 5307.8 | AE6: 5390.2 | AF6: 5073.9 | AG6: 5181.3 | AH6: 5431.3 | AI6: 5729.8 | AJ6: 5906 | AK6: 6239.4 | AL6: 6583.7 | AM6: 6783.2 | AN6: 7126.2 | AO6: 7498 | AP6: 7874.8 | AQ6: 7971.1 | AR6: 8770.6
A7: 5 | B7: Government | C7: 261.5 | D7: 285.8 | E7: 307.5 | F7: 324.8 | G7: 348.1 | H7: 373.9 | I7: 397.2 | J7: 423.1 | K7: 452 | L7: 481.1 | M7: 519 | N7: 548.8 | O7: 572 | P7: 589 | Q7: 609.5 | R7: 629 | S7: 648.1 | T7: 671.9 | U7: 701.3 | V7: 733.8 | W7: 779.8 | X7: 822 | Y7: 872.9 | Z7: 914 | AA7: 952.3 | AB7: 991.3 | AC7: 1034.5 | AD7: 1088.5 | AE7: 1143.9 | AF7: 1175.2 | AG7: 1191.2 | AH7: 1194.9 | AI7: 1198.3 | AJ7: 1208 | AK7: 1236.9 | AL7: 1275.8 | AM7: 1308 | AN7: 1348.2 | AO7: 1401.9 | AP7: 1450.3 | AQ7: 1494.3 | AR7: 1544.4
A8: 6 | B8: Supplements to wages and salaries | C8: 248.8 | D8: 281.2 | E8: 305.5 | F8: 335 | G8: 371 | H8: 404.8 | I8: 439.7 | J8: 466.1 | K8: 508.2 | L8: 556.6 | M8: 599.2 | N8: 636 | O8: 702.7 | P8: 737.9 | Q8: 769.6 | R8: 780.1 | S8: 800.5 | T8: 832 | U8: 889.5 | V8: 944.8 | W8: 1022.2 | X8: 1084.7 | Y8: 1139.3 | Z8: 1215.3 | AA8: 1298.5 | AB8: 1374.7 | AC8: 1422.9 | AD8: 1482.1 | AE8: 1522.7 | AF8: 1509.9 | AG8: 1552.9 | AH8: 1600 | AI8: 1639.2 | AJ8: 1721 | AK8: 1773.9 | AL8: 1839.9 | AM8: 1874.9 | AN8: 1950 | AO8: 2057.6 | AP8: 2121.5 | AQ8: 2132.8 | AR8: 2243.4
A9: 7 | B9: Employer contributions for employee pension and insurance funds1 | C9: 159.9 | D9: 177.5 | E9: 195.7 | F9: 215.1 | G9: 231.9 | H9: 257 | I9: 281.9 | J9: 299.9 | K9: 323.6 | L9: 362.9 | M9: 392.7 | N9: 420.9 | O9: 474.3 | P9: 498.3 | Q9: 515.5 | R9: 515.9 | S9: 525.7 | T9: 542.4 | U9: 582.3 | V9: 621.4 | W9: 677 | X9: 726.7 | Y9: 773.2 | Z9: 832.8 | AA9: 889.7 | AB9: 946.7 | AC9: 975.6 | AD9: 1020.4 | AE9: 1051.3 | AF9: 1051.8 | AG9: 1083.9 | AH9: 1107.3 | AI9: 1125.9 | AJ9: 1194.7 | AK9: 1227.5 | AL9: 1270.6 | AM9: 1293.9 | AN9: 1345.3 | AO9: 1432.8 | AP9: 1470.8 | AQ9: 1474 | AR9: 1536.5
A10: 8 | B10: Employer contributions for government social insurance | C10: 88.9 | D10: 103.6 | E10: 109.8 | F10: 119.9 | G10: 139 | H10: 147.7 | I10: 157.9 | J10: 166.3 | K10: 184.6 | L10: 193.7 | M10: 206.5 | N10: 215.1 | O10: 228.4 | P10: 239.7 | Q10: 254.1 | R10: 264.1 | S10: 274.8 | T10: 289.6 | U10: 307.2 | V10: 323.3 | W10: 345.2 | X10: 358 | Y10: 366 | Z10: 382.5 | AA10: 408.8 | AB10: 428.1 | AC10: 447.3 | AD10: 461.7 | AE10: 471.4 | AF10: 458.1 | AG10: 469 | AH10: 492.7 | AI10: 513.3 | AJ10: 526.3 | AK10: 546.4 | AL10: 569.4 | AM10: 580.9 | AN10: 604.7 | AO10: 624.8 | AP10: 650.6 | AQ10: 658.8 | AR10: 706.9
A11: 9 | B11: Proprietors' income with inventory valuation and capital consumption adjustments | C11: 171.6 | D11: 179.7 | E11: 171.2 | F11: 186.3 | G11: 228.2 | H11: 241.1 | I11: 256.5 | J11: 286.5 | K11: 325.5 | L11: 341.1 | M11: 353.2 | N11: 354.2 | O11: 400.2 | P11: 428 | Q11: 456.6 | R11: 481.2 | S11: 543.8 | T11: 584 | U11: 640.3 | V11: 696.4 | W11: 753.6 | X11: 831.1 | Y11: 870.1 | Z11: 897.5 | AA11: 962.9 | AB11: 979.1 | AC11: 1050.9 | AD11: 995.4 | AE11: 960.3 | AF11: 938.1 | AG11: 1108.5 | AH11: 1228.3 | AI11: 1299.9 | AJ11: 1351.7 | AK11: 1370 | AL11: 1347.7 | AM11: 1349.2 | AN11: 1428.6 | AO11: 1495.3 | AP11: 1555.8 | AQ11: 1599.5 | AR11: 1818.7
A12: 10 | B12: Farm | C12: 11.7 | D12: 19 | E12: 13.3 | F12: 6.2 | G12: 20.9 | H12: 21 | I12: 22.8 | J12: 28.9 | K12: 26.8 | L12: 33 | M12: 32.2 | N12: 26.8 | O12: 34.8 | P12: 31.4 | Q12: 34.7 | R12: 22 | S12: 37.3 | T12: 32.4 | U12: 28.6 | V12: 28 | W12: 31.2 | X12: 32.1 | Y12: 20.3 | Z12: 37.1 | AA12: 52.4 | AB12: 47.9 | AC12: 34.3 | AD12: 41.5 | AE12: 39.5 | AF12: 27.6 | AG12: 38.7 | AH12: 63.9 | AI12: 61 | AJ12: 87.5 | AK12: 68.5 | AL12: 55.5 | AM12: 36 | AN12: 41 | AO12: 32.1 | AP12: 33.8 | AQ12: 51.1 | AR12: 74.5
A13: 11 | B13: Nonfarm | C13: 159.9 | D13: 160.7 | E13: 157.9 | F13: 180.1 | G13: 207.3 | H13: 220.1 | I13: 233.7 | J13: 257.6 | K13: 298.7 | L13: 308.1 | M13: 321 | N13: 327.4 | O13: 365.4 | P13: 396.6 | Q13: 422 | R13: 459.2 | S13: 506.4 | T13: 551.6 | U13: 611.7 | V13: 668.3 | W13: 722.4 | X13: 798.9 | Y13: 849.8 | Z13: 860.4 | AA13: 910.5 | AB13: 931.2 | AC13: 1016.6 | AD13: 953.9 | AE13: 920.8 | AF13: 910.5 | AG13: 1069.8 | AH13: 1164.4 | AI13: 1238.9 | AJ13: 1264.2 | AK13: 1301.5 | AL13: 1292.3 | AM13: 1313.2 | AN13: 1387.6 | AO13: 1463.2 | AP13: 1522 | AQ13: 1548.5 | AR13: 1744.2
A14: 12 | B14: Rental income of persons with capital consumption adjustment | C14: 19 | D14: 23.8 | E14: 23.8 | F14: 24.4 | G14: 24.7 | H14: 26.2 | I14: 18.3 | J14: 16.6 | K14: 22.5 | L14: 21.5 | M14: 28.2 | N14: 38.6 | O14: 60.6 | P14: 90.1 | Q14: 113.7 | R14: 124.9 | S14: 142.5 | T14: 147.1 | U14: 165.2 | V14: 178.5 | W14: 183.5 | X14: 202.4 | Y14: 208.4 | Z14: 227.1 | AA14: 242.8 | AB14: 221.1 | AC14: 181.1 | AD14: 186.3 | AE14: 290.3 | AF14: 347.6 | AG14: 433.7 | AH14: 506.5 | AI14: 534.5 | AJ14: 578.7 | AK14: 598.5 | AL14: 601.4 | AM14: 618.7 | AN14: 642 | AO14: 671.5 | AP14: 688.4 | AQ14: 743.4 | AR14: 776.7
... A37: 35 | B37: Personal saving as a percentage of disposable personal income | C37: 11.1 | D37: 11.7 | E37: 12 | F37: 10.1 | G37: 11.2 | H37: 9.1 | I37: 8.8 | J37: 7.5 | K37: 8.4 | L37: 8.3 | M37: 8.4 | N37: 8.9 | O37: 9.4 | P37: 7.8 | Q37: 6.8 | R37: 6.8 | S37: 6.3 | T37: 6.1 | U37: 6.5 | V37: 4.6 | W37: 4.3 | X37: 4.7 | Y37: 5.6 | Z37: 5.2 | AA37: 4.7 | AB37: 2.2 | AC37: 2.8 | AD37: 2.5 | AE37: 4.1 | AF37: 5.7 | AG37: 5.9 | AH37: 6.5 | AI37: 7.9 | AJ37: 5 | AK37: 5.5 | AL37: 5.8 | AM37: 5.4 | AN37: 5.8 | AO37: 6.4 | AP37: 7.3 | AQ37: 15.3 | AR37: 11.6
B38: Addenda:
A39: 36 | B39: Personal income excluding current transfer receipts, billions of chained (2017) dollars5 | C39: 5251.6 | D39: 5385.4 | E39: 5436.5 | F39: 5564.8 | G39: 5962.3 | H39: 6179.2 | I39: 6403.2 | J39: 6588.1 | K39: 6894.3 | L39: 7119.6 | M39: 7221.1 | N39: 7158 | O39: 7362.7 | P39: 7476.7 | Q39: 7703.8 | R39: 7969.9 | S39: 8290.2 | T39: 8691.1 | U39: 9306.4 | V39: 9656 | W39: 10205.6 | X39: 10359 | Y39: 10309 | Z39: 10443.1 | AA39: 10766.5 | AB39: 10994.3 | AC39: 11473.4 | AD39: 11782 | AE39: 11742.3 | AF39: 11154.8 | AG39: 11303.8 | AH39: 11800.1 | AI39: 12222.9 | AJ39: 12157.4 | AK39: 12605.4 | AL39: 13143.3 | AM39: 13339.5 | AN39: 13807.1 | AO39: 14260 | AP39: 14700.3 | AQ39: 14710 | AR39: 15452.3
B40: Disposable personal income:
A41: 37 | B41: Total, billions of chained (2017) dollars5 | C41: 5201.8 | D41: 5322.2 | E41: 5438.1 | F41: 5632.1 | G41: 6009.2 | H41: 6194.3 | I41: 6430 | J41: 6547.5 | K41: 6878.8 | L41: 7078.6 | M41: 7224.8 | N41: 7286.3 | O41: 7575.9 | P41: 7698.6 | Q41: 7908.6 | R41: 8169.2 | S41: 8423.3 | T41: 8723.8 | U41: 9238 | V41: 9536.9 | W41: 10003.7 | X41: 10297.3 | Y41: 10614.4 | Z41: 10884.3 | AA41: 11233.2 | AB41: 11364.9 | AC41: 11777.6 | AD41: 12054.1 | AE41: 12244.3 | AF41: 12273 | AG41: 12505.3 | AH41: 12775.2 | AI41: 13125.7 | AJ41: 12937.1 | AK41: 13383.7 | AL41: 13908.5 | AM41: 14172 | AN41: 14613.9 | AO41: 15144 | AP41: 15616.5 | AQ41: 16608.4 | AR41: 17252.9
B42: Per capita:
A43: 38 | B43: Current dollars | C43: 8892 | D43: 9815 | E43: 10485 | F43: 11218 | G43: 12313 | H43: 13019 | I43: 13684 | J43: 14236 | K43: 15401 | L43: 16384 | M43: 17262 | N43: 17753 | O43: 18701 | P43: 19226 | Q43: 19919 | R43: 20762 | S43: 21612 | T43: 22502 | U43: 23740 | V43: 24583 | W43: 26151 | X43: 27186 | Y43: 28122 | Z43: 29172 | AA43: 30577 | AB43: 31533 | AC43: 33281 | AD43: 34603 | AE43: 35851 | AF43: 35520 | AG43: 36532 | AH43: 37964 | AI43: 39426 | AJ43: 39077 | AK43: 40671 | AL43: 42013 | AM43: 42910 | AN43: 44710 | AO43: 47002 | AP43: 48907 | AQ43: 52385 | AR43: 56543
A44: 39 | B44: Chained (2017) dollars | C44: 22842 | D44: 23139 | E44: 23418 | F44: 24035 | G44: 25420 | H44: 25971 | I44: 26716 | J44: 26962 | K44: 28070 | L44: 28613 | M44: 28878 | N44: 28739 | O44: 29487 | P44: 29578 | Q44: 30019 | R44: 30644 | S44: 31230 | T44: 31960 | U44: 33452 | V44: 34142 | W44: 35424 | X44: 36102 | Y44: 36861 | Z44: 37451 | AA44: 38304 | AB44: 38396 | AC44: 39414 | AD44: 39954 | AE44: 40205 | AF44: 39946 | AG44: 40361 | AH44: 40908 | AI44: 41705 | AJ44: 40798 | AK44: 41876 | AL44: 43179 | AM44: 43659 | AN44: 44710 | AO44: 46059 | AP44: 47249 | AQ44: 50049 | AR44: 51888
A45: 40 | B45: Population (midperiod, thousands)6 | C45: 227726 | D45: 230008 | E45: 232218 | F45: 234333 | G45: 236394 | H45: 238506 | I45: 240683 | J45: 242843 | K45: 245061 | L45: 247387 | M45: 250181 | N45: 253530 | O45: 256922 | P45: 260282 | Q45: 263455 | R45: 266588 | S45: 269714 | T45: 272958 | U45: 276154 | V45: 279328 | W45: 282398 | X45: 285225 | Y45: 287955 | Z45: 290626 | AA45: 293262 | AB45: 295993 | AC45: 298818 | AD45: 301696 | AE45: 304543 | AF45: 307240 | AG45: 309839 | AH45: 312295 | AI45: 314725 | AJ45: 317099 | AK45: 319601 | AL45: 322113 | AM45: 324609 | AN45: 326860 | AO45: 328794 | AP45: 330513 | AQ45: 331840 | AR45: 332505
B46: Percent change from preceding period:
A47: 41 | B47: Disposable personal income, current dollars | C47: 11.6 | D47: 11.5 | E47: 7.9 | F47: 8 | G47: 10.7 | H47: 6.7 | I47: 6.1 | J47: 5 | K47: 9.2 | L47: 7.4 | M47: 6.5 | N47: 4.2 | O47: 6.7 | P47: 4.2 | Q47: 4.9 | R47: 5.5 | S47: 5.3 | T47: 5.4 | U47: 6.7 | V47: 4.7 | W47: 7.5 | X47: 5 | Y47: 4.4 | Z47: 4.7 | AA47: 5.8 | AB47: 4.1 | AC47: 6.6 | AD47: 5 | AE47: 4.6 | AF47: 0 | AG47: 3.7 | AH47: 4.7 | AI47: 4.7 | AJ47: -0.1 | AK47: 4.9 | AL47: 4.1 | AM47: 2.9 | AN47: 4.9 | AO47: 5.7 | AP47: 4.6 | AQ47: 7.5 | AR47: 8.2
A48: 42 | B48: Personal outlays, current dollars | C48: 10.6 | D48: 10.8 | E48: 7.5 | F48: 10.3 | G48: 9.3 | H48: 9.2 | I48: 6.5 | J48: 6.4 | K48: 8.1 | L48: 7.5 | M48: 6.5 | N48: 3.6 | O48: 6.2 | P48: 5.9 | Q48: 6.1 | R48: 5.4 | S48: 5.9 | T48: 5.7 | U48: 6.3 | V48: 6.8 | W48: 7.9 | X48: 4.6 | Y48: 3.5 | Z48: 5.1 | AA48: 6.4 | AB48: 6.7 | AC48: 6 | AD48: 5.2 | AE48: 2.9 | AF48: -1.7 | AG48: 3.5 | AH48: 4.1 | AI48: 3.2 | AJ48: 3 | AK48: 4.3 | AL48: 3.7 | AM48: 3.5 | AN48: 4.5 | AO48: 5 | AP48: 3.7 | AQ48: -1.8 | AR48: 12.9
A49: 43 | B49: Disposable personal income, chained (2017) dollars | C49: 0.8 | D49: 2.3 | E49: 2.2 | F49: 3.6 | G49: 6.7 | H49: 3.1 | I49: 3.8 | J49: 1.8 | K49: 5.1 | L49: 2.9 | M49: 2.1 | N49: 0.9 | O49: 4 | P49: 1.6 | Q49: 2.7 | R49: 3.3 | S49: 3.1 | T49: 3.6 | U49: 5.9 | V49: 3.2 | W49: 4.9 | X49: 2.9 | Y49: 3.1 | Z49: 2.5 | AA49: 3.2 | AB49: 1.2 | AC49: 3.6 | AD49: 2.3 | AE49: 1.6 | AF49: 0.2 | AG49: 1.9 | AH49: 2.2 | AI49: 2.7 | AJ49: -1.4 | AK49: 3.5 | AL49: 3.9 | AM49: 1.9 | AN49: 3.1 | AO49: 3.6 | AP49: 3.1 | AQ49: 6.4 | AR49: 3.9

Sheet Raw_Unemployment
A1: observation_date | B1: UNRATE
A2: 29221 | B2: 86.1
A3: 29587 | B3: 91.4
A4: 29952 | B4: 116.5
A5: 30317 | B5: 115.2
A6: 30682 | B6: 90.1
A7: 31048 | B7: 86.3
A8: 31413 | B8: 84
A9: 31778 | B9: 74.1
A10: 32143 | B10: 65.9
A11: 32509 | B11: 63.1
A12: 32874 | B12: 67.4
A13: 33239 | B13: 82.2
... A43: 44197 | B43: 64.3
